Workbook

Sheet Lead Tracker
A1: FORREST ANALYTICS GROUP LLC — CLIENT PIPELINE
A2: ID | B2: First Name | C2: Last Name | D2: Institution | E2: PhD Field | F2: Fit | G2: Priority | H2: Email | I2: Date Added | J2: Date Contacted | K2: Follow-up Sent | L2: Status | M2: Last Contact | N2: Next Follow-Up | O2: Notes | P2: Est. Value ($) | Q2: Actual Rev ($) | R2: Days Since Contact | S2: Source
A3: 1 | B3: Existing | C3: Client | D3: Duquesne University | E3: Psychology PhD | F3: High | G3: High | H3: client@duq.edu | I3: 2025-07-01 | J3: 2026-03-15 | K3: YES | L3: Active Client | M3: 2026-03-15 | O3: Race IAT study — full delivery. Request referrals. | P3: 4500 | Q3: 4500 | R3: =IF(J3="","",TODAY()-DATE(LEFT(J3,4)*1,MID(J3,6,2)*1,RIGHT(J3,2)*1))
A4: 2 | B4: Department | C4: Head | D4: Thomas Jefferson University | E4: Nursing PhD | F4: High | G4: High | I4: 2026-04-02 | J4: 2026-04-02 | K4: YES | L4: Nurture | M4: 2026-04-02 | N4: 2026-07-01 | O4: First dissertations ~1 year out. Quarterly check-in. | P4: 3000 | Q4: 0 | R4: =IF(J4="","",TODAY()-DATE(LEFT(J4,4)*1,MID(J4,6,2)*1,RIGHT(J4,2)*1))
A5: 3 | B5: Tory | C5: Benson | D5: Rutgers University - New Brunswick | E5: Social Psychology | F5: High | G5: High | H5: tgb54@scarletmail.rutgers.edu | I5: 2026-04-02 | J5: 2026-04-02 | K5: YES | L5: Contacted | M5: 2026-04-02 | P5: 2500 | Q5: 0 | R5: =IF(J5="","",TODAY()-DATE(LEFT(J5,4)*1,MID(J5,6,2)*1,RIGHT(J5,2)*1))
A6: 4 | B6: Noah | C6: Booker | D6: Rutgers University - New Brunswick | E6: Social Psychology | F6: High | G6: High | H6: nb1157@rutgers.edu | I6: 2026-04-02 | K6: NO | L6: New Lead | P6: 2500 | Q6: 0 | R6: =IF(J6="","",TODAY()-DATE(LEFT(J6,4)*1,MID(J6,6,2)*1,RIGHT(J6,2)*1))
A7: 5 | B7: Clara | C7: Civiero | D7: Rutgers University - New Brunswick | E7: Social Psychology | F7: High | G7: High | H7: clara.civiero@rutgers.edu | I7: 2026-04-02 | K7: NO | L7: New Lead | P7: 2500 | Q7: 0 | R7: =IF(J7="","",TODAY()-DATE(LEFT(J7,4)*1,MID(J7,6,2)*1,RIGHT(J7,2)*1))
A8: 6 | B8: William | C8: Coleman | D8: Rutgers University - New Brunswick | E8: Social Psychology | F8: High | G8: High | H8: willy.coleman@rutgers.edu | I8: 2026-04-02 | K8: NO | L8: New Lead | P8: 2500 | Q8: 0 | R8: =IF(J8="","",TODAY()-DATE(LEFT(J8,4)*1,MID(J8,6,2)*1,RIGHT(J8,2)*1))
A9: 7 | B9: Erin | C9: Foy | D9: Rutgers University - New Brunswick | E9: Social Psychology | F9: High | G9: High | H9: erin.foy@rutgers.edu | I9: 2026-04-02 | K9: NO | L9: New Lead | P9: 2500 | Q9: 0 | R9: =IF(J9="","",TODAY()-DATE(LEFT(J9,4)*1,MID(J9,6,2)*1,RIGHT(J9,2)*1))
A10: 8 | B10: Tamara | C10: Franklin | D10: Rutgers University - New Brunswick | E10: Social Psychology | F10: High | G10: High | H10: tamara.franklin@rutgers.edu | I10: 2026-04-02 | K10: NO | L10: New Lead | P10: 2500 | Q10: 0 | R10: =IF(J10="","",TODAY()-DATE(LEFT(J10,4)*1,MID(J10,6,2)*1,RIGHT(J10,2)*1))
A11: 9 | B11: Vanessa | C11: Hatton | D11: Rutgers University - New Brunswick | E11: Social Psychology | F11: High | G11: High | H11: v.hatton@rutgers.edu | I11: 2026-04-02 | K11: NO | L11: New Lead | P11: 2500 | Q11: 0 | R11: =IF(J11="","",TODAY()-DATE(LEFT(J11,4)*1,MID(J11,6,2)*1,RIGHT(J11,2)*1))
A12: 10 | B12: Selin | C12: Toprakkiran | D12: Rutgers University - New Brunswick | E12: Social Psychology | F12: High | G12: High | H12: selin.t@rutgers.edu | I12: 2026-04-02 | K12: NO | L12: New Lead | P12: 2500 | Q12: 0 | R12: =IF(J12="","",TODAY()-DATE(LEFT(J12,4)*1,MID(J12,6,2)*1,RIGHT(J12,2)*1))
A13: 11 | B13: Grace | C13: Wetzel | D13: Rutgers University - New Brunswick | E13: Social Psychology | F13: High | G13: High | H13: grace.wetzel@rutgers.edu | I13: 2026-04-02 | K13: NO | L13: New Lead | P13: 2500 | Q13: 0 | R13: =IF(J13="","",TODAY()-DATE(LEFT(J13,4)*1,MID(J13,6,2)*1,RIGHT(J13,2)*1))
A14: 12 | B14: Sandra | C14: Manfreda | D14: Rutgers University - New Brunswick | E14: Social Psychology | F14: High | G14: High | H14: sandra.manfreda@rutgers.edu | I14: 2026-04-02 | K14: NO | L14: New Lead | P14: 2500 | Q14: 0 | R14: =IF(J14="","",TODAY()-DATE(LEFT(J14,4)*1,MID(J14,6,2)*1,RIGHT(J14,2)*1))
A15: 13 | B15: Alyssa | C15: Gagnon | D15: Rutgers University | E15: Well-Being Psychology | F15: High | G15: High | H15: alyssa.gagnon@rutgers.edu | I15: 2026-04-02 | J15: 2026-04-02 | K15: YES | L15: Contacted | M15: 2026-04-02 | P15: 2500 | Q15: 0 | R15: =IF(J15="","",TODAY()-DATE(LEFT(J15,4)*1,MID(J15,6,2)*1,RIGHT(J15,2)*1))
A16: 14 | B16: Rowan | C16: Kemmerly | D16: Rutgers University | E16: Well-Being Psychology | F16: High | G16: High | H16: rek102@psychology.rutgers.edu | I16: 2026-04-02 | K16: NO | L16: New Lead | P16: 2500 | Q16: 0 | R16: =IF(J16="","",TODAY()-DATE(LEFT(J16,4)*1,MID(J16,6,2)*1,RIGHT(J16,2)*1))
A17: 15 | B17: Elif | C17: Ulutas | D17: Rutgers University | E17: Well-Being / Health Psychology | F17: High | G17: High | H17: elif.ulutas@rutgers.edu | I17: 2026-04-02 | K17: NO | L17: New Lead | P17: 2500 | Q17: 0 | R17: =IF(J17="","",TODAY()-DATE(LEFT(J17,4)*1,MID(J17,6,2)*1,RIGHT(J17,2)*1))
A18: 16 | B18: Romi | C18: Paldi | D18: Rutgers University | E18: Social Development | F18: Medium | G18: High | H18: romi.paldi@rutgers.edu | I18: 2026-04-02 | K18: NO | L18: New Lead | P18: 2500 | Q18: 0 | R18: =IF(J18="","",TODAY()-DATE(LEFT(J18,4)*1,MID(J18,6,2)*1,RIGHT(J18,2)*1))
A19: 17 | B19: Mary | C19: Mousa | D19: Rutgers University | E19: Social Psychology | F19: High | G19: High | H19: msm299@rutgers.edu | I19: 2026-04-02 | K19: NO | L19: New Lead | P19: 2500 | Q19: 0 | R19: =IF(J19="","",TODAY()-DATE(LEFT(J19,4)*1,MID(J19,6,2)*1,RIGHT(J19,2)*1))
A20: 18 | B20: Sarah | C20: Zhong | D20: Rutgers University | E20: Social Psychology | F20: High | G20: High | H20: yining.zhong@rutgers.edu | I20: 2026-04-02 | K20: NO | L20: New Lead | P20: 2500 | Q20: 0 | R20: =IF(J20="","",TODAY()-DATE(LEFT(J20,4)*1,MID(J20,6,2)*1,RIGHT(J20,2)*1))
A21: 19 | B21: Amanda | C21: Nyakwada | D21: Rutgers University | E21: Decision-Making Psychology | F21: High | G21: High | H21: amanda.nyakwada@rutgers.edu | I21: 2026-04-02 | K21: NO | L21: New Lead | P21: 2500 | Q21: 0 | R21: =IF(J21="","",TODAY()-DATE(LEFT(J21,4)*1,MID(J21,6,2)*1,RIGHT(J21,2)*1))
A22: 20 | B22: Darian | C22: Raizberg | D22: Rutgers University | E22: Decision-Making Psychology | F22: High | G22: High | H22: darian.raizberg@rutgers.edu | I22: 2026-04-02 | K22: NO | L22: New Lead | P22: 2500 | Q22: 0 | R22: =IF(J22="","",TODAY()-DATE(LEFT(J22,4)*1,MID(J22,6,2)*1,RIGHT(J22,2)*1))
A23: 21 | B23: Larissa | C23: Allen | D23: University of Pittsburgh | E23: Nursing / Suicide Research | F23: High | G23: High | H23: lca16@pitt.edu | I23: 2026-04-02 | J23: 2026-04-02 | K23: YES | L23: Contacted | M23: 2026-04-02 | P23: 2500 | Q23: 0 | R23: =IF(J23="","",TODAY()-DATE(LEFT(J23,4)*1,MID(J23,6,2)*1,RIGHT(J23,2)*1))
A24: 22 | B24: Katherine | C24: Cahir | D24: University of Pittsburgh | E24: Nursing / Health Equity | F24: High | G24: High | H24: kmc294@pitt.edu | I24: 2026-04-02 | K24: NO | L24: New Lead | P24: 2500 | Q24: 0 | R24: =IF(J24="","",TODAY()-DATE(LEFT(J24,4)*1,MID(J24,6,2)*1,RIGHT(J24,2)*1))
A25: 23 | B25: Sondos | C25: Eqylan | D25: University of Pittsburgh | E25: Nursing / Caregiving Science | F25: High | G25: High | H25: sbe14@pitt.edu | I25: 2026-04-02 | K25: NO | L25: New Lead | P25: 2500 | Q25: 0 | R25: =IF(J25="","",TODAY()-DATE(LEFT(J25,4)*1,MID(J25,6,2)*1,RIGHT(J25,2)*1))
A26: 24 | B26: Emily | C26: He | D26: University of Pittsburgh | E26: Nursing / Health Equity | F26: High | G26: High | H26: esh87@pitt.edu | I26: 2026-04-02 | K26: NO | L26: New Lead | P26: 2500 | Q26: 0 | R26: =IF(J26="","",TODAY()-DATE(LEFT(J26,4)*1,MID(J26,6,2)*1,RIGHT(J26,2)*1))
A27: 25 | B27: Rezvaneh | C27: Manzour | D27: University of Pittsburgh | E27: Nursing / Mental Health | F27: High | G27: High | H27: rem302@pitt.edu | I27: 2026-04-02 | K27: NO | L27: New Lead | P27: 2500 | Q27: 0 | R27: =IF(J27="","",TODAY()-DATE(LEFT(J27,4)*1,MID(J27,6,2)*1,RIGHT(J27,2)*1))
A28: 26 | B28: Mercy | C28: Opateye | D28: University of Pittsburgh | E28: Nursing / Maternal & Child Health | F28: High | G28: High | H28: mao268@pitt.edu | I28: 2026-04-02 | K28: NO | L28: New Lead | P28: 2500 | Q28: 0 | R28: =IF(J28="","",TODAY()-DATE(LEFT(J28,4)*1,MID(J28,6,2)*1,RIGHT(J28,2)*1))
A29: 27 | B29: Morteza | C29: Shamsizadeh | D29: University of Pittsburgh | E29: Nursing / Palliative Care | F29: High | G29: High | H29: mortyzadeh@pitt.edu | I29: 2026-04-02 | K29: NO | L29: New Lead | P29: 2500 | Q29: 0 | R29: =IF(J29="","",TODAY()-DATE(LEFT(J29,4)*1,MID(J29,6,2)*1,RIGHT(J29,2)*1))
A30: 28 | B30: Kai-Lin | C30: You | D30: University of Pittsburgh | E30: Nursing / Cancer Survivorship | F30: High | G30: High | H30: kailinyou@pitt.edu | I30: 2026-04-02 | K30: NO | L30: New Lead | P30: 2500 | Q30: 0 | R30: =IF(J30="","",TODAY()-DATE(LEFT(J30,4)*1,MID(J30,6,2)*1,RIGHT(J30,2)*1))
A31: 29 | B31: Oluwadunsin | C31: (Esther) Akingbasote | D31: Penn State University | E31: Nursing / Health Equity | F31: High | G31: High | H31: kea5558@psu.edu | I31: 2026-04-02 | J31: 2026-04-02 | K31: YES | L31: Contacted | M31: 2026-04-02 | P31: 2500 | Q31: 0 | R31: =IF(J31="","",TODAY()-DATE(LEFT(J31,4)*1,MID(J31,6,2)*1,RIGHT(J31,2)*1))
A32: 30 | B32: Nahida | C32: Akter | D32: Penn State University | E32: Nursing / Global Health | F32: High | G32: High | H32: nfa5307@psu.edu | I32: 2026-04-02 | K32: NO | L32: New Lead | P32: 2500 | Q32: 0 | R32: =IF(J32="","",TODAY()-DATE(LEFT(J32,4)*1,MID(J32,6,2)*1,RIGHT(J32,2)*1))
A33: 31 | B33: John | C33: Akudugu | D33: Penn State University | E33: Nursing / Public Health | F33: High | G33: High | H33: jma7189@psu.edu | I33: 2026-04-02 | K33: NO | L33: New Lead | P33: 2500 | Q33: 0 | R33: =IF(J33="","",TODAY()-DATE(LEFT(J33,4)*1,MID(J33,6,2)*1,RIGHT(J33,2)*1))
A34: 32 | B34: Samiya | C34: Al Hadhrami | D34: Penn State University | E34: Nursing / Health Services | F34: High | G34: High | H34: sma7174@psu.edu | I34: 2026-04-02 | K34: NO | L34: New Lead | P34: 2500 | Q34: 0 | R34: =IF(J34="","",TODAY()-DATE(LEFT(J34,4)*1,MID(J34,6,2)*1,RIGHT(J34,2)*1))
A35: 33 | B35: Habiba | C35: AL Manji | D35: Penn State University | E35: Nursing / Caregiving | F35: High | G35: High | H35: hpa5265@psu.edu | I35: 2026-04-02 | K35: NO | L35: New Lead | P35: 2500 | Q35: 0 | R35: =IF(J35="","",TODAY()-DATE(LEFT(J35,4)*1,MID(J35,6,2)*1,RIGHT(J35,2)*1))
A36: 34 | B36: Comfort | C36: Asare | D36: Penn State University | E36: Nursing / Maternal & Child Health | F36: High | G36: High | H36: cma6410@psu.edu | I36: 2026-04-02 | K36: NO | L36: New Lead | P36: 2500 | Q36: 0 | R36: =IF(J36="","",TODAY()-DATE(LEFT(J36,4)*1,MID(J36,6,2)*1,RIGHT(J36,2)*1))
A37: 35 | B37: Thakshila | C37: Dasanayake | D37: Penn State University | E37: Nursing / Behavioral Health | F37: High | G37: High | H37: tsd5277@psu.edu | I37: 2026-04-02 | K37: NO | L37: New Lead | P37: 2500 | Q37: 0 | R37: =IF(J37="","",TODAY()-DATE(LEFT(J37,4)*1,MID(J37,6,2)*1,RIGHT(J37,2)*1))
A38: 36 | B38: Myra | C38: DeLuca | D38: Penn State University | E38: Nursing / Clinical Outcomes | F38: High | G38: High | H38: mjj113@psu.edu | I38: 2026-04-02 | K38: NO | L38: New Lead | P38: 2500 | Q38: 0 | R38: =IF(J38="","",TODAY()-DATE(LEFT(J38,4)*1,MID(J38,6,2)*1,RIGHT(J38,2)*1))
A39: 37 | B39: Stephanie | C39: Gigous | D39: Penn State University | E39: Nursing / Health Research | F39: High | G39: High | H39: sln132@psu.edu | I39: 2026-04-02 | K39: NO | L39: New Lead | P39: 2500 | Q39: 0 | R39: =IF(J39="","",TODAY()-DATE(LEFT(J39,4)*1,MID(J39,6,2)*1,RIGHT(J39,2)*1))
A40: 38 | B40: Donya | C40: Hafezi Nia | D40: Penn State University | E40: Nursing / Health Informatics | F40: High | G40: High | H40: djh6767@psu.edu | I40: 2026-04-02 | K40: NO | L40: New Lead | P40: 2500 | Q40: 0 | R40: =IF(J40="","",TODAY()-DATE(LEFT(J40,4)*1,MID(J40,6,2)*1,RIGHT(J40,2)*1))
A41: 39 | B41: Pauline | C41: Hwang | D41: Penn State University | E41: Nursing / Population Health | F41: High | G41: High | H41: pjh232@psu.edu | I41: 2026-04-02 | K41: NO | L41: New Lead | P41: 2500 | Q41: 0 | R41: =IF(J41="","",TODAY()-DATE(LEFT(J41,4)*1,MID(J41,6,2)*1,RIGHT(J41,2)*1))
A42: 40 | B42: Zahra | C42: Karimi | D42: Penn State University | E42: Nursing / Mental Health | F42: High | G42: High | H42: zvk5155@psu.edu | I42: 2026-04-02 | K42: NO | L42: New Lead | P42: 2500 | Q42: 0 | R42: =IF(J42="","",TODAY()-DATE(LEFT(J42,4)*1,MID(J42,6,2)*1,RIGHT(J42,2)*1))
A43: 41 | B43: Naomi | C43: N S Walter | D43: Penn State University | E43: Nursing / Health Services | F43: High | G43: High | H43: nqn5306@psu.edu | I43: 2026-04-02 | K43: NO | L43: New Lead | P43: 2500 | Q43: 0 | R43: =IF(J43="","",TODAY()-DATE(LEFT(J43,4)*1,MID(J43,6,2)*1,RIGHT(J43,2)*1))
... A48: 46 | B48: David | C48: (DJ) Schnabel | D48: Penn State University | E48: Nursing / Clinical Research | F48: High | G48: High | H48: djs7316@psu.edu | I48: 2026-04-02 | K48: NO | L48: New Lead | P48: 2500 | Q48: 0 | R48: =IF(J48="","",TODAY()-DATE(LEFT(J48,4)*1,MID(J48,6,2)*1,RIGHT(J48,2)*1))
A49: 47 | B49: Yodalys | C49: Aguilar | D49: University of North Carolina at Chapel Hill | E49: Social Psychology | F49: High | G49: High | H49: yvaguila@unc.edu | I49: 2026-04-02 | J49: 2026-04-02 | K49: YES | L49: Contacted | M49: 2026-04-02 | P49: 2500 | Q49: 0 | R49: =IF(J49="","",TODAY()-DATE(LEFT(J49,4)*1,MID(J49,6,2)*1,RIGHT(J49,2)*1))
A50: 48 | B50: Natalie | C50: Antenucci | D50: University of North Carolina at Chapel Hill | E50: Social Psychology | F50: High | G50: High | H50: nantenucci@unc.edu | I50: 2026-04-02 | K50: NO | L50: New Lead | P50: 2500 | Q50: 0 | R50: =IF(J50="","",TODAY()-DATE(LEFT(J50,4)*1,MID(J50,6,2)*1,RIGHT(J50,2)*1))
A51: 49 | B51: Adrienne | C51: Bonar | D51: University of North Carolina at Chapel Hill | E51: Social Psychology | F51: High | G51: High | H51: adrienne.bonar@unc.edu | I51: 2026-04-02 | K51: NO | L51: New Lead | P51: 2500 | Q51: 0 | R51: =IF(J51="","",TODAY()-DATE(LEFT(J51,4)*1,MID(J51,6,2)*1,RIGHT(J51,2)*1))
A52: 50 | B52: Megan | C52: Cardenas | D52: University of North Carolina at Chapel Hill | E52: Social Psychology | F52: High | G52: High | H52: mcardenas@unc.edu | I52: 2026-04-02 | K52: NO | L52: New Lead | P52: 2500 | Q52: 0 | R52: =IF(J52="","",TODAY()-DATE(LEFT(J52,4)*1,MID(J52,6,2)*1,RIGHT(J52,2)*1))
A53: 51 | B53: Danica | C53: Dillion | D53: University of North Carolina at Chapel Hill | E53: Social Psychology | F53: High | G53: High | H53: danicaw@email.unc.edu | I53: 2026-04-02 | K53: NO | L53: New Lead | P53: 2500 | Q53: 0 | R53: =IF(J53="","",TODAY()-DATE(LEFT(J53,4)*1,MID(J53,6,2)*1,RIGHT(J53,2)*1))
A54: 52 | B54: Zoe | C54: Hansen | D54: University of North Carolina at Chapel Hill | E54: Social Psychology | F54: High | G54: High | H54: zhansen@unc.edu | I54: 2026-04-02 | K54: NO | L54: New Lead | P54: 2500 | Q54: 0 | R54: =IF(J54="","",TODAY()-DATE(LEFT(J54,4)*1,MID(J54,6,2)*1,RIGHT(J54,2)*1))
A55: 53 | B55: Asha | C55: Hinson | D55: University of North Carolina at Chapel Hill | E55: Social Psychology | F55: High | G55: High | H55: asha.hinson@unc.edu | I55: 2026-04-02 | K55: NO | L55: New Lead | P55: 2500 | Q55: 0 | R55: =IF(J55="","",TODAY()-DATE(LEFT(J55,4)*1,MID(J55,6,2)*1,RIGHT(J55,2)*1))
A56: 54 | B56: Carrington | C56: Merritt | D56: University of North Carolina at Chapel Hill | E56: Social Psychology | F56: High | G56: High | H56: carritt@live.unc.edu | I56: 2026-04-02 | K56: NO | L56: New Lead | P56: 2500 | Q56: 0 | R56: =IF(J56="","",TODAY()-DATE(LEFT(J56,4)*1,MID(J56,6,2)*1,RIGHT(J56,2)*1))
A57: 55 | B57: Maggie | C57: Williams | D57: University of North Carolina at Chapel Hill | E57: Social Psychology | F57: High | G57: High | H57: maggiewi@unc.edu | I57: 2026-04-02 | K57: NO | L57: New Lead | P57: 2500 | Q57: 0 | R57: =IF(J57="","",TODAY()-DATE(LEFT(J57,4)*1,MID(J57,6,2)*1,RIGHT(J57,2)*1))
A58: 56 | B58: Zhiqing | C58: (Michelle) Yang | D58: University of North Carolina at Chapel Hill | E58: Social Psychology | F58: High | G58: High | H58: mzyang@unc.edu | I58: 2026-04-02 | K58: NO | L58: New Lead | P58: 2500 | Q58: 0 | R58: =IF(J58="","",TODAY()-DATE(LEFT(J58,4)*1,MID(J58,6,2)*1,RIGHT(J58,2)*1))
A59: 57 | B59: Katherine | C59: Benson | D59: University of North Carolina at Chapel Hill | E59: Clinical Psychology | F59: High | G59: High | H59: klbenson@ad.unc.edu | I59: 2026-04-02 | K59: NO | L59: New Lead | P59: 2500 | Q59: 0 | R59: =IF(J59="","",TODAY()-DATE(LEFT(J59,4)*1,MID(J59,6,2)*1,RIGHT(J59,2)*1))
A60: 58 | B60: Robin | C60: Brown | D60: University of North Carolina at Chapel Hill | E60: Clinical Psychology | F60: High | G60: High | H60: robindb@unc.edu | I60: 2026-04-02 | K60: NO | L60: New Lead | P60: 2500 | Q60: 0 | R60: =IF(J60="","",TODAY()-DATE(LEFT(J60,4)*1,MID(J60,6,2)*1,RIGHT(J60,2)*1))
A61: 59 | B61: Grace | C61: Cain | D61: University of North Carolina at Chapel Hill | E61: Clinical Psychology | F61: High | G61: High | H61: gcain@unc.edu | I61: 2026-04-02 | K61: NO | L61: New Lead | P61: 2500 | Q61: 0 | R61: =IF(J61="","",TODAY()-DATE(LEFT(J61,4)*1,MID(J61,6,2)*1,RIGHT(J61,2)*1))
... A264: 262 | B264: Mallory | C264: Bates | D264: University of Alabama | E264: Psychology | F264: High | G264: High | H264: mcbates1@crimson.ua.edu | I264: 2026-04-02 | K264: NO | L264: New Lead | P264: 2500 | Q264: 0 | R264: =IF(J264="","",TODAY()-DATE(LEFT(J264,4)*1,MID(J264,6,2)*1,RIGHT(J264,2)*1))
A265: 263 | B265: Beach | D265: University of Alabama | E265: Psychology | F265: High | G265: High | H265: rmbeach2@crimson.ua.edu | I265: 2026-04-02 | K265: NO | L265: New Lead | P265: 2500 | Q265: 0 | R265: =IF(J265="","",TODAY()-DATE(LEFT(J265,4)*1,MID(J265,6,2)*1,RIGHT(J265,2)*1))
A266: 264 | B266: Ava | C266: Behrouzi | D266: University of Alabama | E266: Psychology | F266: High | G266: High | H266: abehrouzi@crimson.ua.edu | I266: 2026-04-02 | K266: NO | L266: New Lead | P266: 2500 | Q266: 0 | R266: =IF(J266="","",TODAY()-DATE(LEFT(J266,4)*1,MID(J266,6,2)*1,RIGHT(J266,2)*1))
A267: 265 | B267: Nick | C267: Bellamy | D267: University of Alabama | E267: Psychology | F267: High | G267: High | H267: nbellamy@crimson.ua.edu | I267: 2026-04-02 | K267: NO | L267: New Lead | P267: 2500 | Q267: 0 | R267: =IF(J267="","",TODAY()-DATE(LEFT(J267,4)*1,MID(J267,6,2)*1,RIGHT(J267,2)*1))
A268: 266 | B268: Kayla | C268: Bird | D268: University of Alabama | E268: Psychology | F268: High | G268: High | H268: kbird2@crimson.ua.edu | I268: 2026-04-02 | K268: NO | L268: New Lead | P268: 2500 | Q268: 0 | R268: =IF(J268="","",TODAY()-DATE(LEFT(J268,4)*1,MID(J268,6,2)*1,RIGHT(J268,2)*1))
A269: 267 | B269: Emmy | C269: Bray | D269: University of Alabama | E269: Psychology | F269: High | G269: High | H269: mebray@crimson.ua.edu | I269: 2026-04-02 | K269: NO | L269: New Lead | P269: 2500 | Q269: 0 | R269: =IF(J269="","",TODAY()-DATE(LEFT(J269,4)*1,MID(J269,6,2)*1,RIGHT(J269,2)*1))
A270: 268 | B270: Justine | C270: Brennan | D270: University of Alabama | E270: Psychology | F270: High | G270: High | H270: jbrennan3@crimson.ua.edu | I270: 2026-04-02 | K270: NO | L270: New Lead | P270: 2500 | Q270: 0 | R270: =IF(J270="","",TODAY()-DATE(LEFT(J270,4)*1,MID(J270,6,2)*1,RIGHT(J270,2)*1))
A271: 269 | B271: Johnna | C271: Brown | D271: University of Alabama | E271: Psychology | F271: High | G271: High | H271: jbrown66@crimson.ua.edu | I271: 2026-04-02 | K271: NO | L271: New Lead | P271: 2500 | Q271: 0 | R271: =IF(J271="","",TODAY()-DATE(LEFT(J271,4)*1,MID(J271,6,2)*1,RIGHT(J271,2)*1))
A272: 270 | B272: Emma | C272: Bumgardner | D272: University of Alabama | E272: Psychology | F272: High | G272: High | H272: epbumgardner@crimson.ua.edu | I272: 2026-04-02 | K272: NO | L272: New Lead | P272: 2500 | Q272: 0 | R272: =IF(J272="","",TODAY()-DATE(LEFT(J272,4)*1,MID(J272,6,2)*1,RIGHT(J272,2)*1))
A273: 271 | B273: Michael | C273: Buxton | D273: University of Alabama | E273: Psychology | F273: High | G273: High | H273: mrbuxton1@crimson.ua.edu | I273: 2026-04-02 | K273: NO | L273: New Lead | P273: 2500 | Q273: 0 | R273: =IF(J273="","",TODAY()-DATE(LEFT(J273,4)*1,MID(J273,6,2)*1,RIGHT(J273,2)*1))
A274: 272 | B274: Sidra | C274: Capriolo | D274: University of Alabama | E274: Psychology | F274: High | G274: High | H274: smcapriolo@crimson.ua.edu | I274: 2026-04-02 | K274: NO | L274: New Lead | P274: 2500 | Q274: 0 | R274: =IF(J274="","",TODAY()-DATE(LEFT(J274,4)*1,MID(J274,6,2)*1,RIGHT(J274,2)*1))
A275: 273 | B275: Erick | C275: Carranza | D275: University of Alabama | E275: Psychology | F275: High | G275: High | H275: ecarranza@crimson.ua.edu | I275: 2026-04-02 | K275: NO | L275: New Lead | P275: 2500 | Q275: 0 | R275: =IF(J275="","",TODAY()-DATE(LEFT(J275,4)*1,MID(J275,6,2)*1,RIGHT(J275,2)*1))
A276: 274 | B276: Jack | C276: Cassell | D276: University of Alabama | E276: Psychology | F276: High | G276: High | H276: jacassell@crimson.ua.edu | I276: 2026-04-02 | K276: NO | L276: New Lead | P276: 2500 | Q276: 0 | R276: =IF(J276="","",TODAY()-DATE(LEFT(J276,4)*1,MID(J276,6,2)*1,RIGHT(J276,2)*1))
A277: 275 | B277: Harriet | C277: DeGroot | D277: University of Alabama | E277: Psychology | F277: High | G277: High | H277: hrdegroot@crimson.ua.edu | I277: 2026-04-02 | K277: NO | L277: New Lead | P277: 2500 | Q277: 0 | R277: =IF(J277="","",TODAY()-DATE(LEFT(J277,4)*1,MID(J277,6,2)*1,RIGHT(J277,2)*1))
... A560: 558 | B560: August | C560: Yu | D560: Fordham University | E560: Philosophy | F560: Low | G560: Low | H560: lyu64@fordham.edu | I560: 2026-04-02 | K560: NO | L560: New Lead | P560: 2500 | Q560: 0 | R560: =IF(J560="","",TODAY()-DATE(LEFT(J560,4)*1,MID(J560,6,2)*1,RIGHT(J560,2)*1))
A561: 559 | B561: A | C561: Plus Air Services | F561: Unknown | G561: Medium | H561: ductworkcleaningservices@gmail.com | I561: 2026-04-02 | K561: NO | L561: New Lead | P561: 2500 | Q561: 0 | R561: =IF(J561="","",TODAY()-DATE(LEFT(J561,4)*1,MID(J561,6,2)*1,RIGHT(J561,2)*1))
A562: 560 | B562: Ya-Li | C562: Yang | D562: Virginia Commonwealth University | E562: Social Work PhD | F562: High | G562: High | H562: yangy11@vcu.edu | I562: 2026-04-03 | K562: NO | L562: New Lead | P562: 2500 | Q562: 0 | R562: =IF(J562="","",TODAY()-DATE(LEFT(J562,4)*1,MID(J562,6,2)*1,RIGHT(J562,2)*1)) | S562: University Website
A563: 561 | B563: Jeff | C563: Ciak | D563: Virginia Commonwealth University | E563: Social Work PhD | F563: High | G563: High | H563: ciakj@vcu.edu | I563: 2026-04-03 | K563: NO | L563: New Lead | P563: 2500 | Q563: 0 | R563: =IF(J563="","",TODAY()-DATE(LEFT(J563,4)*1,MID(J563,6,2)*1,RIGHT(J563,2)*1)) | S563: University Website
A564: 562 | B564: Katie | C564: Kim | D564: Virginia Commonwealth University | E564: Social Work PhD | F564: High | G564: High | H564: kimk15@vcu.edu | I564: 2026-04-03 | K564: NO | L564: New Lead | P564: 2500 | Q564: 0 | R564: =IF(J564="","",TODAY()-DATE(LEFT(J564,4)*1,MID(J564,6,2)*1,RIGHT(J564,2)*1)) | S564: University Website
A565: 563 | B565: Reem | C565: Shawkat | D565: Virginia Commonwealth University | E565: Social Work PhD | F565: High | G565: High | H565: shawkatra@vcu.edu | I565: 2026-04-03 | K565: NO | L565: New Lead | P565: 2500 | Q565: 0 | R565: =IF(J565="","",TODAY()-DATE(LEFT(J565,4)*1,MID(J565,6,2)*1,RIGHT(J565,2)*1)) | S565: University Website
A566: 564 | B566: Samuel | C566: Ochinang | D566: Virginia Commonwealth University | E566: Social Work PhD | F566: High | G566: High | H566: ochinangsa@vcu.edu | I566: 2026-04-03 | K566: NO | L566: New Lead | O566: Constructed email | P566: 2500 | Q566: 0 | R566: =IF(J566="","",TODAY()-DATE(LEFT(J566,4)*1,MID(J566,6,2)*1,RIGHT(J566,2)*1)) | S566: University Website
A567: 565 | B567: Rayelle | C567: Ross | D567: Virginia Commonwealth University | E567: Social Work PhD | F567: High | G567: High | H567: rossra@vcu.edu | I567: 2026-04-03 | K567: NO | L567: New Lead | O567: Constructed email | P567: 2500 | Q567: 0 | R567: =IF(J567="","",TODAY()-DATE(LEFT(J567,4)*1,MID(J567,6,2)*1,RIGHT(J567,2)*1)) | S567: University Website
A568: 566 | B568: Kade | C568: Goldin | D568: Virginia Commonwealth University | E568: Social Work PhD | F568: High | G568: High | H568: goldink@vcu.edu | I568: 2026-04-03 | K568: NO | L568: New Lead | O568: Constructed email | P568: 2500 | Q568: 0 | R568: =IF(J568="","",TODAY()-DATE(LEFT(J568,4)*1,MID(J568,6,2)*1,RIGHT(J568,2)*1)) | S568: University Website
A569: 567 | B569: Marianne | C569: Lund | D569: Virginia Commonwealth University | E569: Social Work PhD | F569: High | G569: High | H569: lundma@vcu.edu | I569: 2026-04-03 | K569: NO | L569: New Lead | O569: Constructed email | P569: 2500 | Q569: 0 | R569: =IF(J569="","",TODAY()-DATE(LEFT(J569,4)*1,MID(J569,6,2)*1,RIGHT(J569,2)*1)) | S569: University Website
A570: 568 | B570: Allison | C570: Borek | D570: Duke University | E570: Nursing PhD | F570: High | G570: High | H570: allison.borek@duke.edu | I570: 2026-04-03 | K570: NO | L570: New Lead | O570: Constructed email; Jonas Scholar research focus: cancer care disparities | P570: 2500 | Q570: 0 | R570: =IF(J570="","",TODAY()-DATE(LEFT(J570,4)*1,MID(J570,6,2)*1,RIGHT(J570,2)*1)) | S570: University Website
A571: 569 | B571: Kevin | C571: Gao | D571: Duke University | E571: Nursing PhD | F571: High | G571: High | H571: kevin.gao@duke.edu | I571: 2026-04-03 | K571: NO | L571: New Lead | O571: Constructed email; Jonas Scholar 2024-2026; social determinants & stroke care | P571: 2500 | Q571: 0 | R571: =IF(J571="","",TODAY()-DATE(LEFT(J571,4)*1,MID(J571,6,2)*1,RIGHT(J571,2)*1)) | S571: University Website
A572: 570 | B572: Bonnie | C572: Hunt | D572: Duke University | E572: Nursing PhD | F572: High | G572: High | H572: bonnie.hunt@duke.edu | I572: 2026-04-03 | K572: NO | L572: New Lead | O572: Constructed email; Jonas Scholar 2024-2026; transportation insecurity & surgery | P572: 2500 | Q572: 0 | R572: =IF(J572="","",TODAY()-DATE(LEFT(J572,4)*1,MID(J572,6,2)*1,RIGHT(J572,2)*1)) | S572: University Website
A573: 571 | B573: Jill | C573: Sergison | D573: Duke University | E573: Nursing PhD | F573: High | G573: High | H573: jill.sergison@duke.edu | I573: 2026-04-03 | K573: NO | L573: New Lead | O573: Constructed email; cervical cancer screening & trust in Appalachia | P573: 2500 | Q573: 0 | R573: =IF(J573="","",TODAY()-DATE(LEFT(J573,4)*1,MID(J573,6,2)*1,RIGHT(J573,2)*1)) | S573: University Website
A574: 572 | B574: Olivia | C574: Short | D574: Duke University | E574: Nursing PhD | F574: High | G574: High | H574: olivia.short@duke.edu | I574: 2026-04-03 | K574: NO | L574: New Lead | O574: Constructed email; clinical research nurse background | P574: 2500 | Q574: 0 | R574: =IF(J574="","",TODAY()-DATE(LEFT(J574,4)*1,MID(J574,6,2)*1,RIGHT(J574,2)*1)) | S574: University Website
A575: 573 | B575: Aderonke | C575: Kareem | D575: Duke University | E575: Nursing PhD | F575: High | G575: High | H575: aderonke.kareem@duke.edu | I575: 2026-04-03 | K575: NO | L575: New Lead | O575: Constructed email; sickle cell disease & chronic pain disparities | P575: 2500 | Q575: 0 | R575: =IF(J575="","",TODAY()-DATE(LEFT(J575,4)*1,MID(J575,6,2)*1,RIGHT(J575,2)*1)) | S575: University Website
A576: 574 | B576: Jolie | C576: Jemmott | D576: Duke University | E576: Nursing PhD | F576: High | G576: High | H576: jolie.jemmott@duke.edu | I576: 2026-04-03 | K576: NO | L576: New Lead | O576: Constructed email; psychiatric MHNP; African American men dual diagnosis | P576: 2500 | Q576: 0 | R576: =IF(J576="","",TODAY()-DATE(LEFT(J576,4)*1,MID(J576,6,2)*1,RIGHT(J576,2)*1)) | S576: University Website
A577: 575 | B577: Luke | C577: Velickoff | D577: Duke University | E577: Nursing PhD | F577: High | G577: High | H577: luke.velickoff@duke.edu | I577: 2026-04-03 | K577: NO | L577: New Lead | O577: Constructed email; transgender & gender-diverse acute care | P577: 2500 | Q577: 0 | R577: =IF(J577="","",TODAY()-DATE(LEFT(J577,4)*1,MID(J577,6,2)*1,RIGHT(J577,2)*1)) | S577: University Website
... A598: 596 | B598: Mitchell | C598: Knisely | D598: Duke University | E598: Program Director | F598: High | G598: High | H598: mitchell.knisely@duke.edu | I598: 2026-04-03 | K598: NO | L598: New Lead | O598: Asst. Dean & PhD Program Director, School of Nursing. Referral target — ask to share FAG with current doctoral cohort. Research: sickle cell & chronic pain. | P598: 10000 | Q598: 0 | R598: =IF(J598="","",TODAY()-DATE(LEFT(J598,4)*1,MID(J598,6,2)*1,RIGHT(J598,2)*1)) | S598: University Website
A599: 597 | B599: Maddy | C599: Finkelstein | D599: Drexel University | E599: Public Health PhD | F599: High | G599: A | H599: maddy.finkelstein@drexel.edu | I599: 2026-04-03 | L599: New Lead | O599: Dornsife SPH; email constructed | P599: 2500 | S599: University Website
A600: 598 | B600: Bengucan | C600: Gunen | D600: Drexel University | E600: Public Health PhD | F600: High | G600: A | H600: bengucan.gunen@drexel.edu | I600: 2026-04-03 | L600: New Lead | O600: CHP; ASN pre-doctoral fellow; email constructed | P600: 2500 | S600: University Website
A601: 599 | B601: Patrick | C601: Smith | D601: Drexel University | E601: Public Health PhD | F601: High | G601: A | H601: patrick.smith@drexel.edu | I601: 2026-04-03 | L601: New Lead | O601: CHP PhD '25; NHLBI NRSA fellow; email constructed | P601: 2500 | S601: University Website
A602: 600 | B602: Kati | C602: Hinman | D602: Drexel University | E602: Public Health PhD | F602: High | G602: A | H602: kati.hinman@drexel.edu | I602: 2026-04-03 | L602: New Lead | O602: CHP; Fulbright-Hays DDRA 2023-24; email constructed | P602: 2500 | S602: University Website
A603: 601 | B603: Katherine | C603: Dilks-Webb | D603: Drexel University | E603: Nursing PhD | F603: High | G603: A | H603: katherine.dilks-webb@drexel.edu | I603: 2026-04-03 | L603: New Lead | O603: CNHP; featured PhD research page; email constructed | P603: 2500 | S603: University Website
A604: 602 | B604: Grant | C604: Morales | D604: Drexel University | E604: Nursing PhD | F604: High | G604: A | H604: grant.morales@drexel.edu | I604: 2026-04-03 | L604: New Lead | O604: CNHP; email constructed | P604: 2500 | S604: University Website
A605: 603 | B605: Elizabeth | C605: Euiler | D605: Drexel University | E605: Nursing PhD | F605: High | G605: A | H605: elizabeth.euiler@drexel.edu | I605: 2026-04-03 | L605: New Lead | O605: CNHP; featured PhD research page; email constructed | P605: 2500 | S605: University Website
A606: 604 | B606: Ana Lucia | C606: Peralta | D606: Drexel University | E606: Public Health PhD | F606: High | G606: A | H606: ana.peralta@drexel.edu | I606: 2026-04-03 | L606: New Lead | O606: Epidemiology; Urban Health Collaborative; email constructed | P606: 2500 | S606: University Website
A607: 605 | B607: Abbey | C607: Collins | D607: NC State University | E607: Psychology PhD | F607: High | G607: A | H607: abbey_collins@ncsu.edu | I607: 2026-04-03 | L607: New Lead | O607: Applied Social & Community Psych; Fall 2022; Black Health Lab; email constructed | P607: 2500 | S607: University Website
A608: 606 | B608: Alexis | C608: Briggs | D608: NC State University | E608: Psychology PhD | F608: High | G608: A | H608: alexis_briggs@ncsu.edu | I608: 2026-04-03 | L608: New Lead | O608: Applied Social & Community Psych; Fall 2019; Hope Lab; email constructed | P608: 2500 | S608: University Website
...

Sheet Email Templates
A1: FORREST ANALYTICS GROUP LLC — OUTREACH EMAIL TEMPLATES
A2: FORMAT RULES: 50-125 words max | 3-7 word subject | One CTA question | No em dashes | No bullets | Sound human | Link website naturally
A3: TEMPLATE 1 -- Cold Outreach - Psychology / Social Psych PhD | B3: Cold Outreach -- Psychology / Social Psych PhD
A4: Subject | B4: quick question about your dissertation
A5: Body | B5: Hi [First Name], I came across your profile through the [University] psychology program and wanted to reach out. I run Forrest Analytics Group (forrestanalyticsgroup.com) and I help PhD candidates with the data side of dissertations -- things like Qualtrics setup, R or Python analysis, and the stats for the results chapter. I just finished a project like that for a psych PhD candidate at Duquesne and it went really well. Are you at a stage where that kind of support might be useful? Josh Forrest 856.725.4983
A6: Word Count | B6: ~75 words
A8: TEMPLATE 2 -- Cold Outreach - Nursing / Public Health PhD | B8: Cold Outreach -- Nursing / Public Health PhD
A9: Subject | B9: dissertation data support -- nursing research
A10: Body | B10: Hi [First Name], I found you through the [University] nursing program and wanted to reach out. I work with nursing and public health PhD candidates on the technical parts of their dissertations -- Qualtrics survey setup, data cleaning in R, and statistical analysis for the results chapter. I run Forrest Analytics Group (forrestanalyticsgroup.com) and recently completed a full data support project for another doctoral candidate. Are you approaching your data collection or analysis phase? Josh Forrest 856.725.4983
A11: Word Count | B11: ~80 words
A13: TEMPLATE 3 -- Cold Outreach - Behavior Analysis / Clinical Science | B13: Cold Outreach -- Behavior Analysis / Clinical Science
A14: Subject | B14: data help for your dissertation
A15: Body | B15: Hi [First Name], I run Forrest Analytics Group (forrestanalyticsgroup.com) and work with doctoral candidates on the technical parts of dissertation research -- survey design, data cleaning, and statistical analysis in R and Python. I found you through the [University] program and thought this might be relevant to where you are in your research. I recently supported a PhD candidate at Duquesne through the full analysis phase. Would a quick 15-minute call be worth it? Josh Forrest 856.725.4983
A16: Word Count | B16: ~80 words
... A36: Word Count | B36: ~55 words

Sheet Dashboard
A1: PIPELINE DASHBOARD
A3: PIPELINE SUMMARY
A4: Metric | B4: Count | C4: Est. Value ($) | D4: Actual Rev ($)
A5: Total Leads | B5: =COUNTA('Lead Tracker'!A3:A2000) | C5: =SUMIF('Lead Tracker'!L3:L2000,"<>Closed Lost",'Lead Tracker'!P3:P2000) | D5: =SUM('Lead Tracker'!Q3:Q2000)
A6: High Priority | B6: =COUNTIF('Lead Tracker'!G3:G2000,"High")
A7: New (Not Contacted) | B7: =COUNTIF('Lead Tracker'!L3:L2000,"New Lead")
A8: Contacted | B8: =COUNTIF('Lead Tracker'!L3:L2000,"Contacted")
A9: Active Clients | B9: =COUNTIF('Lead Tracker'!L3:L2000,"Active Client") | C9: =SUMIF('Lead Tracker'!L3:L2000,"Active Client",'Lead Tracker'!P3:P2000) | D9: =SUMIF('Lead Tracker'!L3:L2000,"Active Client",'Lead Tracker'!Q3:Q2000)
A10: Closed Won | B10: =COUNTIF('Lead Tracker'!L3:L2000,"Closed Won") | D10: =SUMIF('Lead Tracker'!L3:L2000,"Closed Won",'Lead Tracker'!Q3:Q2000)
A11: Nurture | B11: =COUNTIF('Lead Tracker'!L3:L2000,"Nurture")
A14: REVENUE GOALS
A15: Monthly Revenue Target ($) | B15: 2000
A16: Total Actual Revenue ($) | B16: =SUM('Lead Tracker'!Q3:Q2000)
A17: Total Pipeline Value ($) | B17: =SUMIF('Lead Tracker'!L3:L2000,"<>Closed Lost",'Lead Tracker'!P3:P2000)
A20: LEAD PRIORITY BREAKDOWN
A21: High Priority Leads | B21: =COUNTIF('Lead Tracker'!G3:G2000,"High")
A22: Medium Priority Leads | B22: =COUNTIF('Lead Tracker'!G3:G2000,"Medium")
A23: Low Priority Leads | B23: =COUNTIF('Lead Tracker'!G3:G2000,"Low")
