Workbook

Sheet README
A1: KEYSTONE PLUMBING & DRAIN — Sample Operational Dataset
A3: Prepared by: Forrest Analytics Group LLC
A4: Use: Case-study dataset for AI implementation portfolio (service-business vertical)
A5: Generated: 2026-04-07
A7: Business profile (fictional):
A8: • Founded 2014, Philadelphia metro (Main Line + Western Suburbs)
A9: • 8 technicians, 5 service trucks, ~$2.1M annual revenue
A10: • Mix: ~75% residential, ~15% commercial, ~10% property mgmt
A11: • Services: plumbing, drain, water heater, sewer, sump pump, light HVAC
A13: Sheets in this workbook:
A14: • Customers — 850 records (residential, commercial, property mgmt)
A15: • Jobs — 2400 records spanning ~24 months
... A21: • Summary — KPI rollup with formulas

Sheet Customers
A1: Customer ID | B1: Name | C1: Type | D1: Phone | E1: Email | F1: Address | G1: City | H1: State | I1: Zip | J1: Lead Source | K1: Created | L1: Lifetime Jobs
A2: C-10001 | B2: Christine Anderson | C2: Residential | D2: (494) 289-7912 | E2: christine.anderson30@gmail.com | F2: 509 Madison Ln | G2: King of Prussia | H2: PA | I2: 19438 | J2: Google Search | K2: 2024-03-13 | L2: 3
A3: C-10002 | B3: Brenda Sanchez | C3: Residential | D3: (572) 632-6574 | E3: brenda.sanchez98@outlook.com | F3: 9028 Garden Blvd | G3: Norristown | H3: PA | I3: 19485 | J3: Repeat Customer | K3: 2023-12-30 | L3: 3
A4: C-10003 | B4: Susan Lopez | C4: Residential | D4: (278) 587-2291 | E4: susan_lopez@comcast.net | F4: 6324 Cedar Dr | G4: Ardmore | H4: PA | I4: 19087 | J4: Angi | K4: 2024-01-01 | L4: 1
A5: C-10004 | B5: Pamela Harris | C5: Residential | D5: (540) 573-3664 | E5: pamela_harris35@outlook.com | F5: 1239 Oak Blvd | G5: Wayne | H5: PA | I5: 19020 | J5: Google Search | K5: 2023-11-01 | L5: 1
A6: C-10005 | B6: Perez Management | C6: Commercial | D6: (381) 986-1916 | E6: samantha.perez@yahoo.com | F6: 8851 Madison Blvd | G6: Conshohocken | H6: PA | I6: 19469 | J6: HomeAdvisor | K6: 2024-06-20 | L6: 1
A7: C-10006 | B7: Rodriguez Plaza | C7: Property Mgmt | D7: (341) 962-9830 | E7: paulrodriguez@outlook.com | F7: 3556 Baltimore Dr | G7: King of Prussia | H7: PA | I7: 19493 | J7: HomeAdvisor | K7: 2024-06-17 | L7: 1
A8: C-10007 | B8: George Lewis | C8: Residential | D8: (431) 810-2040 | E8: george_lewis@hotmail.com | F8: 2366 Lombard Pl | G8: Bryn Mawr | H8: PA | I8: 19016 | J8: Direct Mail | K8: 2025-11-01 | L8: 3
A9: C-10008 | B9: Allen Management | C9: Commercial | D9: (437) 361-8433 | E9: helenallen@gmail.com | F9: 9164 Franklin St | G9: West Chester | H9: PA | I9: 19324 | J9: Repeat Customer | K9: 2024-02-09 | L9: 1
A10: C-10009 | B10: Thompson Realty | C10: Commercial | D10: (491) 997-9689 | E10: nicholasthompson@gmail.com | F10: 8417 Baltimore Ave | G10: West Chester | H10: PA | I10: 19348 | J10: Google Search | K10: 2025-09-15 | L10: 3
A11: C-10010 | B11: Joseph Campbell | C11: Residential | D11: (604) 745-3060 | E11: josephcampbell@yahoo.com | F11: 5138 Spruce St | G11: King of Prussia | H11: PA | I11: 19482 | J11: Facebook | K11: 2026-01-09 | L11: 4
A12: C-10011 | B12: Kimberly Ortiz | C12: Residential | D12: (547) 582-8177 | E12: kimberly_ortiz29@comcast.net | F12: 7032 Chestnut Way | G12: Drexel Hill | H12: PA | I12: 19098 | J12: Google Search | K12: 2024-04-06 | L12: 12
A13: C-10012 | B13: Amanda Williams | C13: Residential | D13: (249) 232-6413 | E13: amandawilliams86@gmail.com | F13: 9738 Pine Blvd | G13: Media | H13: PA | I13: 19038 | J13: Truck Signage | K13: 2026-01-24 | L13: 1
... A851: C-10850 | B851: Stephanie Allen | C851: Residential | D851: (492) 432-7590 | E851: stephanieallen@yahoo.com | F851: 2726 Broad St | G851: Bala Cynwyd | H851: PA | I851: 19048 | J851: HomeAdvisor | K851: 2026-02-22 | L851: 2

Sheet Jobs
A1: Job ID | B1: Customer ID | C1: Customer Name | D1: Job Type | E1: Category | F1: Priority | G1: Scheduled | H1: Completed | I1: Status | J1: Tech ID | K1: Tech Name | L1: Hours | M1: Revenue | N1: Parts Cost | O1: Labor Cost | P1: COGS | Q1: Margin | R1: Rating | S1: City | T1: Zip
A2: J-20001 | B2: C-10432 | C2: Karen Hill | D2: Frozen Pipe Thaw | E2: Emergency | F2: Emergency | G2: 2024-05-25 11:52 | H2: 2024-05-25 11:52 | I2: Completed | J2: T-04 | K2: Brandon Pierce | L2: 1.47 | M2: 665.95 | N2: 150.91 | O2: 79.56 | P2: 230.47 | Q2: 435.48 | S2: Bryn Mawr | T2: 19091
A3: J-20002 | B3: C-10747 | C3: Michelle Hernandez | D3: Slab Leak Repair | E3: Repair | F3: Standard | G3: 2025-02-12 12:19 | H3: 2025-02-12 12:19 | I3: Completed | J3: T-08 | K3: Marcus Thompson | L3: 6.4 | M3: 3927.93 | N3: 799.67 | O3: 368.07 | P3: 1167.74 | Q3: 2760.19 | S3: Bala Cynwyd | T3: 19021
A4: J-20003 | B4: C-10794 | C4: Anthony Flores | D4: Boiler Repair | E4: HVAC | F4: Standard | G4: 2025-03-09 07:33 | H4: 2025-03-09 07:33 | I4: Completed | J4: T-07 | K4: Kevin O'Brien | L4: 2.83 | M4: 569.33 | N4: 140.56 | O4: 139.32 | P4: 279.88 | Q4: 289.45 | R4: 1 | S4: Chester | T4: 19087
A5: J-20004 | B5: C-10697 | C5: Adams Management | D5: Backflow Testing | E5: Inspection | F5: Standard | G5: 2025-09-16 19:34 | H5: 2025-09-16 19:34 | I5: Completed | J5: T-08 | K5: Marcus Thompson | L5: 0.71 | M5: 257.31 | N5: 68.83 | O5: 42.97 | P5: 111.8 | Q5: 145.51 | S5: West Chester | T5: 19357
A6: J-20005 | B6: C-10628 | C6: Cruz Group | D6: Hydro Jetting | E6: Drain | F6: Standard | G6: 2026-03-29 22:39 | H6: 2026-03-30 22:39 | I6: Completed | J6: T-04 | K6: Brandon Pierce | L6: 2.38 | M6: 763.09 | N6: 229.69 | O6: 112.61 | P6: 342.3 | Q6: 420.79 | S6: West Chester | T6: 19347
A7: J-20006 | B7: C-10315 | C7: Scott Hill | D7: Furnace Repair | E7: HVAC | F7: Standard | G7: 2025-01-04 08:39 | H7: 2025-01-04 08:39 | I7: Completed | J7: T-03 | K7: Tyrese Jackson | L7: 0.98 | M7: 275.18 | N7: 72.47 | O7: 52.45 | P7: 124.92 | Q7: 150.26 | R7: 5 | S7: Bryn Mawr | T7: 19017
A8: J-20007 | B8: C-10546 | C8: Mary Davis | D8: Water Softener Install | E8: Install | F8: Standard | G8: 2025-07-25 20:18 | H8: 2025-07-27 20:18 | I8: Completed | J8: T-01 | K8: Mike Sullivan | L8: 2.92 | M8: 2004.42 | N8: 563.18 | O8: 153.57 | P8: 716.75 | Q8: 1287.67 | R8: 5 | S8: West Chester | T8: 19384
A9: J-20008 | B9: C-10175 | C9: William Mitchell | D9: HVAC Tune-Up | E9: HVAC | F9: Standard | G9: 2025-01-10 05:24 | I9: Scheduled | J9: T-06 | K9: David Chen | L9: 1.76 | M9: 151 | N9: 42.02 | O9: 118.07 | P9: 160.09 | Q9: -9.09 | S9: West Chester | T9: 19349
A10: J-20009 | B10: C-10088 | C10: George Mitchell | D10: Sump Pump Install | E10: Install | F10: Standard | G10: 2024-05-22 17:20 | I10: Cancelled | J10: T-02 | K10: Carlos Mendez | L10: 3.37 | M10: 872.59 | N10: 183.71 | O10: 165.25 | P10: 348.96 | Q10: 523.63 | S10: Ardmore | T10: 19096
A11: J-20010 | B11: C-10819 | C11: Donna Evans | D11: Kitchen Remodel Plumbing | E11: Project | F11: Standard | G11: 2025-10-15 12:06 | I11: Scheduled | J11: T-01 | K11: Mike Sullivan | L11: 12.68 | M11: 2317.81 | N11: 753.15 | O11: 713.62 | P11: 1466.77 | Q11: 851.04 | S11: Wayne | T11: 19055
A12: J-20011 | B12: C-10171 | C12: Sarah Evans | D12: Water Heater Replacement | E12: Install | F12: Standard | G12: 2025-07-01 00:12 | H12: 2025-07-01 00:12 | I12: Completed | J12: T-01 | K12: Mike Sullivan | L12: 3.47 | M12: 1818.36 | N12: 634.82 | O12: 187.77 | P12: 822.59 | Q12: 995.77 | S12: Drexel Hill | T12: 19026
A13: J-20012 | B13: C-10640 | C13: Jason White | D13: Drain Cleaning | E13: Drain | F13: Standard | G13: 2024-12-11 11:36 | H13: 2024-12-11 11:36 | I13: Completed | J13: T-06 | K13: David Chen | L13: 0.69 | M13: 361.31 | N13: 44.95 | O13: 38.14 | P13: 83.09 | Q13: 278.22 | S13: King of Prussia | T13: 19494
A14: J-20013 | B14: C-10803 | C14: Gonzalez LLC | D14: Frozen Pipe Thaw | E14: Emergency | F14: Emergency | G14: 2024-11-22 14:43 | H14: 2024-11-22 14:43 | I14: Completed | J14: T-06 | K14: David Chen | L14: 1.62 | M14: 662.16 | N14: 188.98 | O14: 97.06 | P14: 286.04 | Q14: 376.12 | S14: Conshohocken | T14: 19438
A15: J-20014 | B15: C-10117 | C15: Garcia Building | D15: Drain Cleaning | E15: Drain | F15: Standard | G15: 2026-01-20 18:37 | H15: 2026-01-20 18:37 | I15: Completed | J15: T-02 | K15: Carlos Mendez | L15: 1.13 | M15: 379.58 | N15: 115.94 | O15: 54.12 | P15: 170.06 | Q15: 209.52 | R15: 5 | S15: Drexel Hill | T15: 19052
A16: J-20015 | B16: C-10827 | C16: Wright Center | D16: Faucet Replacement | E16: Install | F16: Standard | G16: 2024-12-21 03:05 | H16: 2024-12-21 03:05 | I16: Completed | J16: T-01 | K16: Mike Sullivan | L16: 1.24 | M16: 216.25 | N16: 57.09 | O16: 84.97 | P16: 142.06 | Q16: 74.19 | R16: 4 | S16: Norristown | T16: 19489
A17: J-20016 | B17: C-10084 | C17: Helen Rogers | D17: Leaking Pipe Repair | E17: Repair | F17: Standard | G17: 2024-05-04 16:47 | H17: 2024-05-04 16:47 | I17: Completed | J17: T-04 | K17: Brandon Pierce | L17: 1.12 | M17: 266.27 | N17: 90.22 | O17: 50.52 | P17: 140.74 | Q17: 125.53 | R17: 1 | S17: Ardmore | T17: 19092
A18: J-20017 | B18: C-10620 | C18: Ryan Jones | D18: Gas Line Repair | E18: Repair | F18: Standard | G18: 2025-09-29 08:00 | I18: Completed | J18: T-04 | K18: Brandon Pierce | L18: 2.7 | M18: 969.88 | N18: 309.35 | O18: 125.97 | P18: 435.32 | Q18: 534.56 | S18: Conshohocken | T18: 19491
A19: J-20018 | B19: C-10078 | C19: James White | D19: Burst Pipe Emergency | E19: Emergency | F19: Emergency | G19: 2025-10-22 11:20 | H19: 2025-10-23 11:20 | I19: Completed | J19: T-05 | K19: Anthony Russo | L19: 3.57 | M19: 740.32 | N19: 143.57 | O19: 256.27 | P19: 399.84 | Q19: 340.48 | R19: 5 | S19: Bryn Mawr | T19: 19028
A20: J-20019 | B20: C-10354 | C20: Sharon Reed | D20: Water Main Repair | E20: Emergency | F20: Emergency | G20: 2025-10-23 21:57 | H20: 2025-10-23 21:57 | I20: Completed | J20: T-07 | K20: Kevin O'Brien | L20: 8.01 | M20: 6925.42 | N20: 1919.81 | O20: 421.32 | P20: 2341.13 | Q20: 4584.29 | R20: 4 | S20: Conshohocken | T20: 19494
A21: J-20020 | B21: C-10734 | C21: Jeffrey Campbell | D21: Bathroom Remodel Plumbing | E21: Project | F21: Standard | G21: 2024-08-12 12:16 | H21: 2024-08-12 12:16 | I21: Completed | J21: T-05 | K21: Anthony Russo | L21: 16.47 | M21: 2917.79 | N21: 849.61 | O21: 780.39 | P21: 1630 | Q21: 1287.79 | R21: 5 | S21: Media | T21: 19049
A22: J-20021 | B22: C-10831 | C22: Baker Management | D22: Kitchen Remodel Plumbing | E22: Project | F22: Standard | G22: 2025-08-16 05:50 | H22: 2025-08-16 05:50 | I22: Completed | J22: T-08 | K22: Marcus Thompson | L22: 10.26 | M22: 4328.62 | N22: 1062.94 | O22: 668.07 | P22: 1731.01 | Q22: 2597.61 | S22: Ardmore | T22: 19032
A23: J-20022 | B23: C-10413 | C23: Jeffrey Kim | D23: Bathroom Remodel Plumbing | E23: Project | F23: Standard | G23: 2025-03-08 10:59 | H23: 2025-03-09 10:59 | I23: Completed | J23: T-03 | K23: Tyrese Jackson | L23: 18.46 | M23: 7758.06 | N23: 1759.61 | O23: 906.8 | P23: 2666.41 | Q23: 5091.65 | R23: 4 | S23: Conshohocken | T23: 19448
A24: J-20023 | B24: C-10678 | C24: Matthew Clark | D24: Leaking Pipe Repair | E24: Repair | F24: Standard | G24: 2025-07-03 13:48 | H24: 2025-07-03 13:48 | I24: Completed | J24: T-05 | K24: Anthony Russo | L24: 2.03 | M24: 322.65 | N24: 39.93 | O24: 117.24 | P24: 157.17 | Q24: 165.48 | S24: Chester | T24: 19055
A25: J-20024 | B25: C-10742 | C25: Brian Torres | D25: Kitchen Remodel Plumbing | E25: Project | F25: Standard | G25: 2024-05-25 22:38 | H25: 2024-05-28 22:38 | I25: Completed | J25: T-08 | K25: Marcus Thompson | L25: 17.89 | M25: 4089.64 | N25: 1381.83 | O25: 882.25 | P25: 2264.08 | Q25: 1825.56 | R25: 5 | S25: Chester | T25: 19044
A26: J-20025 | B26: C-10507 | C26: Robert Moore | D26: AC Repair | E26: HVAC | F26: Standard | G26: 2025-05-23 02:21 | H26: 2025-05-23 02:21 | I26: Completed | J26: T-05 | K26: Anthony Russo | L26: 2.12 | M26: 952.21 | N26: 252.57 | O26: 114.78 | P26: 367.35 | Q26: 584.86 | R26: 4 | S26: Ardmore | T26: 19036
A27: J-20026 | B27: C-10132 | C27: Joseph Clark | D27: Sump Pump Install | E27: Install | F27: Standard | G27: 2025-03-24 10:45 | H27: 2025-03-24 10:45 | I27: Completed | J27: T-06 | K27: David Chen | L27: 3.85 | M27: 1091.4 | N27: 249.83 | O27: 175.09 | P27: 424.92 | Q27: 666.48 | S27: Chester | T27: 19067
A28: J-20027 | B28: C-10488 | C28: Richardson Management | D28: AC Repair | E28: HVAC | F28: Standard | G28: 2025-05-12 03:24 | H28: 2025-05-15 03:24 | I28: Completed | J28: T-04 | K28: Brandon Pierce | L28: 1.91 | M28: 828.3 | N28: 232.43 | O28: 132.46 | P28: 364.89 | Q28: 463.41 | R28: 5 | S28: Philadelphia | T28: 19117
A29: J-20028 | B29: C-10020 | C29: Paul Torres | D29: Faucet Replacement | E29: Install | F29: Standard | G29: 2024-07-07 13:55 | H29: 2024-07-07 13:55 | I29: Completed | J29: T-05 | K29: Anthony Russo | L29: 1.22 | M29: 287.19 | N29: 40.78 | O29: 79.61 | P29: 120.39 | Q29: 166.8 | R29: 5 | S29: King of Prussia | T29: 19497
A30: J-20029 | B30: C-10789 | C30: Edwards Holdings | D30: Sewer Line Repair | E30: Repair | F30: Urgent | G30: 2026-04-03 13:38 | H30: 2026-04-04 13:38 | I30: Completed | J30: T-05 | K30: Anthony Russo | L30: 5.66 | M30: 5466.58 | N30: 1251.64 | O30: 288.83 | P30: 1540.47 | Q30: 3926.11 | S30: Norristown | T30: 19439
A31: J-20030 | B31: C-10322 | C31: Steven Perez | D31: Water Softener Install | E31: Install | F31: Standard | G31: 2025-09-26 04:22 | H31: 2025-09-26 04:22 | I31: Completed | J31: T-04 | K31: Brandon Pierce | L31: 3.08 | M31: 2309.86 | N31: 383.47 | O31: 206.02 | P31: 589.49 | Q31: 1720.37 | S31: Drexel Hill | T31: 19089
A32: J-20031 | B32: C-10255 | C32: Robinson Plaza | D32: AC Repair | E32: HVAC | F32: Standard | G32: 2025-06-07 23:59 | H32: 2025-06-07 23:59 | I32: Completed | J32: T-08 | K32: Marcus Thompson | L32: 1.45 | M32: 873.05 | N32: 164.64 | O32: 73.25 | P32: 237.89 | Q32: 635.16 | S32: Norristown | T32: 19490
A33: J-20032 | B33: C-10458 | C33: White Building | D33: Slab Leak Detection | E33: Diagnostic | F33: Standard | G33: 2025-05-20 20:01 | H33: 2025-05-20 20:01 | I33: Completed | J33: T-08 | K33: Marcus Thompson | L33: 2.55 | M33: 499.61 | N33: 77.99 | O33: 145.33 | P33: 223.32 | Q33: 276.29 | S33: West Chester | T33: 19323
A34: J-20033 | B34: C-10331 | C34: Ronald Ward | D34: Drain Cleaning | E34: Drain | F34: Standard | G34: 2025-03-18 06:59 | H34: 2025-03-18 06:59 | I34: Completed | J34: T-06 | K34: David Chen | L34: 1.36 | M34: 317.62 | N34: 65.06 | O34: 72.78 | P34: 137.84 | Q34: 179.78 | S34: Chester | T34: 19092
A35: J-20034 | B35: C-10660 | C35: Brandon Thomas | D35: Garbage Disposal Install | E35: Install | F35: Standard | G35: 2024-10-30 22:14 | H35: 2024-10-30 22:14 | I35: Completed | J35: T-02 | K35: Carlos Mendez | L35: 2.03 | M35: 362.76 | N35: 106.65 | O35: 93.51 | P35: 200.16 | Q35: 162.6 | R35: 5 | S35: Media | T35: 19054
A36: J-20035 | B36: C-10731 | C36: Martinez Holdings | D36: Sewer Line Inspection | E36: Diagnostic | F36: Standard | G36: 2026-01-25 08:35 | H36: 2026-01-25 08:35 | I36: Completed | J36: T-07 | K36: Kevin O'Brien | L36: 1.2 | M36: 296.42 | N36: 41.1 | O36: 65.13 | P36: 106.23 | Q36: 190.19 | S36: Norristown | T36: 19464
A37: J-20036 | B37: C-10092 | C37: Jeffrey Ward | D37: Furnace Repair | E37: HVAC | F37: Standard | G37: 2025-07-13 16:45 | H37: 2025-07-13 16:45 | I37: Completed | J37: T-04 | K37: Brandon Pierce | L37: 2.26 | M37: 382.51 | N37: 59.89 | O37: 148.24 | P37: 208.13 | Q37: 174.38 | R37: 4 | S37: King of Prussia | T37: 19478
A38: J-20037 | B38: C-10157 | C38: Clark Center | D38: Boiler Repair | E38: HVAC | F38: Standard | G38: 2024-10-31 14:29 | H38: 2024-10-31 14:29 | I38: Completed | J38: T-02 | K38: Carlos Mendez | L38: 3.43 | M38: 760.97 | N38: 202.34 | O38: 191.01 | P38: 393.35 | Q38: 367.62 | S38: Drexel Hill | T38: 19018
A39: J-20038 | B39: C-10214 | C39: Alexander Walker | D39: Sewer Line Inspection | E39: Diagnostic | F39: Standard | G39: 2024-08-19 12:28 | H39: 2024-08-20 12:28 | I39: Completed | J39: T-01 | K39: Mike Sullivan | L39: 1.17 | M39: 341.55 | N39: 41.55 | O39: 74.82 | P39: 116.37 | Q39: 225.18 | S39: Wayne | T39: 19057
A40: J-20039 | B40: C-10289 | C40: Ronald Gonzalez | D40: Sewer Line Repair | E40: Repair | F40: Standard | G40: 2025-04-29 17:40 | H40: 2025-04-30 17:40 | I40: Completed | J40: T-08 | K40: Marcus Thompson | L40: 4.32 | M40: 2593.36 | N40: 431.44 | O40: 265.27 | P40: 696.71 | Q40: 1896.65 | S40: Wayne | T40: 19070
A41: J-20040 | B41: C-10668 | C41: Benjamin Flores | D41: Slab Leak Repair | E41: Repair | F41: Standard | G41: 2026-02-23 11:09 | I41: Completed | J41: T-05 | K41: Anthony Russo | L41: 5.38 | M41: 3206.28 | N41: 683.93 | O41: 268.95 | P41: 952.88 | Q41: 2253.4 | S41: Media | T41: 19098
A42: J-20041 | B42: C-10608 | C42: Thompson Building | D42: Furnace Repair | E42: HVAC | F42: Standard | G42: 2025-07-22 17:28 | H42: 2025-07-22 17:28 | I42: Completed | J42: T-06 | K42: David Chen | L42: 1.82 | M42: 717.35 | N42: 124 | O42: 125.64 | P42: 249.64 | Q42: 467.71 | S42: Bala Cynwyd | T42: 19064
A43: J-20042 | B43: C-10398 | C43: Howard Building | D43: Water Main Repair | E43: Emergency | F43: Emergency | G43: 2025-10-19 08:30 | I43: Scheduled | J43: T-04 | K43: Brandon Pierce | L43: 10.11 | M43: 3968.63 | N43: 1374.63 | O43: 619.23 | P43: 1993.86 | Q43: 1974.77 | S43: Norristown | T43: 19485
A44: J-20043 | B44: C-10080 | C44: Brian Parker | D44: Water Softener Install | E44: Install | F44: Standard | G44: 2025-06-30 23:41 | I44: Cancelled | J44: T-02 | K44: Carlos Mendez | L44: 4.02 | M44: 1287.44 | N44: 169.31 | O44: 182.12 | P44: 351.43 | Q44: 936.01 | S44: Chester | T44: 19095
A45: J-20044 | B45: C-10221 | C45: Linda Kim | D45: Slab Leak Detection | E45: Diagnostic | F45: Standard | G45: 2026-01-19 15:34 | H45: 2026-01-19 15:34 | I45: Completed | J45: T-02 | K45: Carlos Mendez | L45: 2.01 | M45: 442.24 | N45: 96.11 | O45: 138.01 | P45: 234.12 | Q45: 208.12 | R45: 2 | S45: West Chester | T45: 19327
A46: J-20045 | B46: C-10820 | C46: Peterson Properties | D46: Burst Pipe Emergency | E46: Emergency | F46: Emergency | G46: 2024-12-05 19:00 | H46: 2024-12-05 19:00 | I46: Completed | J46: T-05 | K46: Anthony Russo | L46: 3.78 | M46: 1785.06 | N46: 539.69 | O46: 259.94 | P46: 799.63 | Q46: 985.43 | R46: 4 | S46: Ardmore | T46: 19032
A47: J-20046 | B47: C-10492 | C47: Thompson Apartments | D47: Water Heater Repair | E47: Repair | F47: Urgent | G47: 2024-05-12 11:59 | H47: 2024-05-12 11:59 | I47: Completed | J47: T-03 | K47: Tyrese Jackson | L47: 1.87 | M47: 404.43 | N47: 62.79 | O47: 87.44 | P47: 150.23 | Q47: 254.2 | S47: Ardmore | T47: 19034
A48: J-20047 | B48: C-10046 | C48: Kim Management | D48: Slab Leak Repair | E48: Repair | F48: Standard | G48: 2025-07-07 23:18 | H48: 2025-07-07 23:18 | I48: Completed | J48: T-08 | K48: Marcus Thompson | L48: 8.37 | M48: 2594.18 | N48: 479.3 | O48: 484.94 | P48: 964.24 | Q48: 1629.94 | S48: Bala Cynwyd | T48: 19067
A49: J-20048 | B49: C-10046 | C49: Kim Management | D49: Boiler Repair | E49: HVAC | F49: Standard | G49: 2024-04-17 08:10 | H49: 2024-04-17 08:10 | I49: Completed | J49: T-06 | K49: David Chen | L49: 3.5 | M49: 958.61 | N49: 303.98 | O49: 210.32 | P49: 514.3 | Q49: 444.31 | R49: 3 | S49: Bala Cynwyd | T49: 19067
A50: J-20049 | B50: C-10558 | C50: Ronald Gomez | D50: Leaking Pipe Repair | E50: Repair | F50: Standard | G50: 2024-06-21 12:34 | H50: 2024-06-21 12:34 | I50: Completed | J50: T-06 | K50: David Chen | L50: 0.93 | M50: 551.79 | N50: 134.84 | O50: 49.9 | P50: 184.74 | Q50: 367.05 | R50: 4 | S50: Wayne | T50: 19099
A51: J-20050 | B51: C-10507 | C51: Robert Moore | D51: Slab Leak Repair | E51: Repair | F51: Standard | G51: 2024-07-29 15:04 | H51: 2024-07-29 15:04 | I51: Completed | J51: T-08 | K51: Marcus Thompson | L51: 8.31 | M51: 3287.01 | N51: 666.85 | O51: 470.81 | P51: 1137.66 | Q51: 2149.35 | S51: Ardmore | T51: 19036
A52: J-20051 | B52: C-10169 | C52: Joshua Jones | D52: Water Heater Replacement | E52: Install | F52: Standard | G52: 2024-06-28 00:50 | I52: Scheduled | J52: T-04 | K52: Brandon Pierce | L52: 3.11 | M52: 2825.8 | N52: 433.37 | O52: 168.64 | P52: 602.01 | Q52: 2223.79 | S52: Bryn Mawr | T52: 19066
A53: J-20052 | B53: C-10406 | C53: Carter LLC | D53: Water Heater Repair | E53: Repair | F53: Standard | G53: 2024-09-26 22:27 | H53: 2024-09-26 22:27 | I53: Completed | J53: T-03 | K53: Tyrese Jackson | L53: 2.2 | M53: 432.03 | N53: 139.36 | O53: 157.84 | P53: 297.2 | Q53: 134.83 | S53: West Chester | T53: 19344
A54: J-20053 | B54: C-10807 | C54: Stephen Collins | D54: Faucet Replacement | E54: Install | F54: Standard | G54: 2024-10-18 02:08 | H54: 2024-10-18 02:08 | I54: Completed | J54: T-02 | K54: Carlos Mendez | L54: 0.78 | M54: 352.29 | N54: 72.52 | O54: 54.83 | P54: 127.35 | Q54: 224.94 | S54: Chester | T54: 19043
A55: J-20054 | B55: C-10160 | C55: Brian Brown | D55: Furnace Repair | E55: HVAC | F55: Standard | G55: 2024-11-06 20:29 | I55: Cancelled | J55: T-04 | K55: Brandon Pierce | L55: 2.03 | M55: 752.4 | N55: 220.65 | O55: 130.61 | P55: 351.26 | Q55: 401.14 | S55: Bala Cynwyd | T55: 19020
A56: J-20055 | B56: C-10311 | C56: Susan Perez | D56: Furnace Repair | E56: HVAC | F56: Standard | G56: 2025-06-08 20:47 | H56: 2025-06-08 20:47 | I56: Completed | J56: T-05 | K56: Anthony Russo | L56: 2.18 | M56: 948.18 | N56: 155.44 | O56: 99.05 | P56: 254.49 | Q56: 693.69 | R56: 2 | S56: Chester | T56: 19053
A57: J-20056 | B57: C-10678 | C57: Matthew Clark | D57: Sump Pump Repair | E57: Repair | F57: Standard | G57: 2025-03-19 17:41 | H57: 2025-03-19 17:41 | I57: Completed | J57: T-01 | K57: Mike Sullivan | L57: 2.02 | M57: 227.75 | N57: 58.63 | O57: 109.62 | P57: 168.25 | Q57: 59.5 | S57: Chester | T57: 19055
A58: J-20057 | B58: C-10512 | C58: Garcia Plaza | D58: Faucet Replacement | E58: Install | F58: Urgent | G58: 2025-12-27 10:16 | I58: Cancelled | J58: T-08 | K58: Marcus Thompson | L58: 0.89 | M58: 279.72 | N58: 84.9 | O58: 58.14 | P58: 143.04 | Q58: 136.68 | S58: Bala Cynwyd | T58: 19067
A59: J-20058 | B59: C-10390 | C59: Ashley Adams | D59: Water Heater Replacement | E59: Install | F59: Standard | G59: 2025-07-22 06:55 | H59: 2025-07-22 06:55 | I59: Completed | J59: T-02 | K59: Carlos Mendez | L59: 5.19 | M59: 2797.88 | N59: 824.2 | O59: 245.72 | P59: 1069.92 | Q59: 1727.96 | S59: Media | T59: 19029
A60: J-20059 | B60: C-10248 | C60: Miller Apartments | D60: Water Softener Install | E60: Install | F60: Standard | G60: 2025-08-28 04:34 | H60: 2025-08-28 04:34 | I60: Completed | J60: T-01 | K60: Mike Sullivan | L60: 4.26 | M60: 1621.78 | N60: 484.5 | O60: 290 | P60: 774.5 | Q60: 847.28 | S60: West Chester | T60: 19350
A61: J-20060 | B61: C-10515 | C61: Robinson Realty | D61: Leaking Pipe Repair | E61: Repair | F61: Standard | G61: 2024-10-05 03:14 | H61: 2024-10-05 03:14 | I61: Completed | J61: T-08 | K61: Marcus Thompson | L61: 1.49 | M61: 433.43 | N61: 121.51 | O61: 82.67 | P61: 204.18 | Q61: 229.25 | S61: Norristown | T61: 19439
A62: J-20061 | B62: C-10167 | C62: Laura Cruz | D62: Water Heater Replacement | E62: Install | F62: Standard | G62: 2025-09-15 08:29 | H62: 2025-09-15 08:29 | I62: Completed | J62: T-03 | K62: Tyrese Jackson | L62: 4.25 | M62: 1603.54 | N62: 249.52 | O62: 287.34 | P62: 536.86 | Q62: 1066.68 | R62: 5 | S62: Media | T62: 19013
A63: J-20062 | B63: C-10349 | C63: Paul Jackson | D63: Boiler Repair | E63: HVAC | F63: Standard | G63: 2025-01-06 01:02 | H63: 2025-01-06 01:02 | I63: Completed | J63: T-01 | K63: Mike Sullivan | L63: 3.65 | M63: 1093.41 | N63: 343.85 | O63: 186.79 | P63: 530.64 | Q63: 562.77 | R63: 4 | S63: Conshohocken | T63: 19419
A64: J-20063 | B64: C-10022 | C64: Sharon Taylor | D64: Gas Line Repair | E64: Repair | F64: Standard | G64: 2025-06-25 10:25 | H64: 2025-06-25 10:25 | I64: Completed | J64: T-06 | K64: David Chen | L64: 1.55 | M64: 934.13 | N64: 134.94 | O64: 89.57 | P64: 224.51 | Q64: 709.62 | S64: Philadelphia | T64: 19155
A65: J-20064 | B65: C-10250 | C65: Jennifer Martin | D65: Toilet Install | E65: Install | F65: Standard | G65: 2024-05-26 17:32 | H65: 2024-05-26 17:32 | I65: Completed | J65: T-08 | K65: Marcus Thompson | L65: 1.88 | M65: 426.14 | N65: 67.01 | O65: 113.55 | P65: 180.56 | Q65: 245.58 | S65: West Chester | T65: 19388
A66: J-20065 | B66: C-10190 | C66: William Howard | D66: Backflow Testing | E66: Inspection | F66: Standard | G66: 2024-04-18 12:00 | H66: 2024-04-18 12:00 | I66: Completed | J66: T-05 | K66: Anthony Russo | L66: 0.54 | M66: 192.87 | N66: 29.68 | O66: 26.24 | P66: 55.92 | Q66: 136.95 | R66: 3 | S66: West Chester | T66: 19360
A67: J-20066 | B67: C-10141 | C67: Ashley Cox | D67: Faucet Replacement | E67: Install | F67: Standard | G67: 2025-09-25 02:30 | H67: 2025-09-25 02:30 | I67: Completed | J67: T-02 | K67: Carlos Mendez | L67: 1.17 | M67: 369.15 | N67: 117.37 | O67: 77.96 | P67: 195.33 | Q67: 173.82 | R67: 5 | S67: Chester | T67: 19051
A68: J-20067 | B68: C-10779 | C68: Margaret Gonzalez | D68: Water Heater Repair | E68: Repair | F68: Standard | G68: 2025-02-07 03:37 | H68: 2025-02-09 03:37 | I68: Completed | J68: T-07 | K68: Kevin O'Brien | L68: 0.5 | M68: 206.78 | N68: 32.65 | O68: 30.96 | P68: 63.61 | Q68: 143.17 | R68: 5 | S68: Media | T68: 19072
A69: J-20068 | B69: C-10198 | C69: Justin Robinson | D69: Slab Leak Repair | E69: Repair | F69: Standard | G69: 2025-08-19 00:02 | H69: 2025-08-19 00:02 | I69: Completed | J69: T-07 | K69: Kevin O'Brien | L69: 6.64 | M69: 3775.21 | N69: 777.49 | O69: 379.45 | P69: 1156.94 | Q69: 2618.27 | S69: West Chester | T69: 19340
A70: J-20069 | B70: C-10162 | C70: Brenda Diaz | D70: Sewer Line Inspection | E70: Diagnostic | F70: Standard | G70: 2026-01-29 06:55 | H70: 2026-01-29 06:55 | I70: Completed | J70: T-01 | K70: Mike Sullivan | L70: 0.83 | M70: 379.62 | N70: 83.34 | O70: 38.04 | P70: 121.38 | Q70: 258.24 | R70: 5 | S70: West Chester | T70: 19333
A71: J-20070 | B71: C-10827 | C71: Wright Center | D71: Faucet Replacement | E71: Install | F71: Standard | G71: 2025-05-26 08:28 | H71: 2025-05-26 08:28 | I71: Completed | J71: T-03 | K71: Tyrese Jackson | L71: 0.88 | M71: 245.7 | N71: 59.73 | O71: 47.37 | P71: 107.1 | Q71: 138.6 | R71: 5 | S71: Norristown | T71: 19489
A72: J-20071 | B72: C-10351 | C72: Richard Collins | D72: Camera Inspection | E72: Diagnostic | F72: Standard | G72: 2025-06-15 04:28 | H72: 2025-06-15 04:28 | I72: Completed | J72: T-04 | K72: Brandon Pierce | L72: 0.65 | M72: 220.22 | N72: 40.01 | O72: 34.01 | P72: 74.02 | Q72: 146.2 | R72: 5 | S72: Norristown | T72: 19439
A73: J-20072 | B73: C-10846 | C73: Ronald Carter | D73: Faucet Replacement | E73: Install | F73: Standard | G73: 2025-01-27 02:18 | H73: 2025-01-27 02:18 | I73: Completed | J73: T-05 | K73: Anthony Russo | L73: 0.96 | M73: 288.53 | N73: 61.93 | O73: 50.04 | P73: 111.97 | Q73: 176.56 | S73: Bryn Mawr | T73: 19038
A74: J-20073 | B74: C-10730 | C74: Kelly Group | D74: Camera Inspection | E74: Diagnostic | F74: Standard | G74: 2025-06-12 03:45 | H74: 2025-06-12 03:45 | I74: Completed | J74: T-03 | K74: Tyrese Jackson | L74: 0.84 | M74: 249.78 | N74: 59.85 | O74: 40.46 | P74: 100.31 | Q74: 149.47 | S74: Drexel Hill | T74: 19088
A75: J-20074 | B75: C-10384 | C75: Jessica Ortiz | D75: Sewer Line Inspection | E75: Diagnostic | F75: Standard | G75: 2024-12-22 06:39 | H75: 2024-12-22 06:39 | I75: Completed | J75: T-07 | K75: Kevin O'Brien | L75: 0.94 | M75: 303.33 | N75: 86.42 | O75: 65.97 | P75: 152.39 | Q75: 150.94 | S75: Chester | T75: 19074
A76: J-20075 | B76: C-10004 | C76: Pamela Harris | D76: Water Heater Repair | E76: Repair | F76: Standard | G76: 2024-08-17 15:28 | H76: 2024-08-17 15:28 | I76: Completed | J76: T-07 | K76: Kevin O'Brien | L76: 1.83 | M76: 463.34 | N76: 104.06 | O76: 131.31 | P76: 235.37 | Q76: 227.97 | S76: Wayne | T76: 19020
A77: J-20076 | B77: C-10111 | C77: Clark Management | D77: Kitchen Remodel Plumbing | E77: Project | F77: Standard | G77: 2025-12-02 12:12 | H77: 2025-12-03 12:12 | I77: Completed | J77: T-05 | K77: Anthony Russo | L77: 18.49 | M77: 4107.98 | N77: 788.83 | O77: 901.81 | P77: 1690.64 | Q77: 2417.34 | S77: Norristown | T77: 19490
A78: J-20077 | B78: C-10131 | C78: Ashley Kim | D78: AC Repair | E78: HVAC | F78: Standard | G78: 2026-02-04 23:53 | H78: 2026-02-04 23:53 | I78: Completed | J78: T-07 | K78: Kevin O'Brien | L78: 2.68 | M78: 546.68 | N78: 70.62 | O78: 168.38 | P78: 239 | Q78: 307.68 | R78: 4 | S78: Chester | T78: 19056
A79: J-20078 | B79: C-10770 | C79: Gomez Plaza | D79: Sewer Line Repair | E79: Repair | F79: Standard | G79: 2026-03-14 06:23 | H79: 2026-03-14 06:23 | I79: Completed | J79: T-07 | K79: Kevin O'Brien | L79: 7.4 | M79: 6164.51 | N79: 1241.02 | O79: 380.23 | P79: 1621.25 | Q79: 4543.26 | S79: Drexel Hill | T79: 19075
A80: J-20079 | B80: C-10165 | C80: Anderson Realty | D80: Water Heater Repair | E80: Repair | F80: Standard | G80: 2025-07-28 10:46 | H80: 2025-07-28 10:46 | I80: Completed | J80: T-04 | K80: Brandon Pierce | L80: 1.03 | M80: 477.23 | N80: 146.13 | O80: 49.81 | P80: 195.94 | Q80: 281.29 | R80: 4 | S80: Chester | T80: 19059
A81: J-20080 | B81: C-10446 | C81: Rivera Realty | D81: Backflow Testing | E81: Inspection | F81: Standard | G81: 2025-08-12 20:06 | H81: 2025-08-12 20:06 | I81: Completed | J81: T-07 | K81: Kevin O'Brien | L81: 0.64 | M81: 268.31 | N81: 84.63 | O81: 36.51 | P81: 121.14 | Q81: 147.17 | S81: Philadelphia | T81: 19142
A82: J-20081 | B82: C-10024 | C82: Flores Holdings | D82: Camera Inspection | E82: Diagnostic | F82: Standard | G82: 2025-04-21 13:59 | H82: 2025-04-21 13:59 | I82: Completed | J82: T-04 | K82: Brandon Pierce | L82: 1.02 | M82: 279.26 | N82: 61.56 | O82: 70 | P82: 131.56 | Q82: 147.7 | S82: West Chester | T82: 19334
A83: J-20082 | B83: C-10616 | C83: Barbara Thompson | D83: Furnace Repair | E83: HVAC | F83: Standard | G83: 2025-09-06 17:40 | H83: 2025-09-06 17:40 | I83: Completed | J83: T-04 | K83: Brandon Pierce | L83: 1.66 | M83: 756.19 | N83: 156.43 | O83: 110.02 | P83: 266.45 | Q83: 489.74 | S83: Wayne | T83: 19066
A84: J-20083 | B84: C-10025 | C84: King Holdings | D84: Slab Leak Repair | E84: Repair | F84: Standard | G84: 2025-03-04 05:38 | H84: 2025-03-04 05:38 | I84: Completed | J84: T-08 | K84: Marcus Thompson | L84: 7.03 | M84: 3698.59 | N84: 828.55 | O84: 468.22 | P84: 1296.77 | Q84: 2401.82 | R84: 5 | S84: Philadelphia | T84: 19123
A85: J-20084 | B85: C-10235 | C85: Wilson LLC | D85: Sewer Line Repair | E85: Repair | F85: Standard | G85: 2025-10-16 16:06 | H85: 2025-10-16 16:06 | I85: Completed | J85: T-04 | K85: Brandon Pierce | L85: 5.56 | M85: 3554.67 | N85: 1241.76 | O85: 322.04 | P85: 1563.8 | Q85: 1990.87 | S85: Media | T85: 19096
A86: J-20085 | B86: C-10374 | C86: John Roberts | D86: Water Heater Replacement | E86: Install | F86: Standard | G86: 2026-02-14 15:55 | H86: 2026-02-14 15:55 | I86: Completed | J86: T-03 | K86: Tyrese Jackson | L86: 4.53 | M86: 2732.19 | N86: 385.91 | O86: 288.89 | P86: 674.8 | Q86: 2057.39 | R86: 3 | S86: Bala Cynwyd | T86: 19083
A87: J-20086 | B87: C-10235 | C87: Wilson LLC | D87: Frozen Pipe Thaw | E87: Emergency | F87: Emergency | G87: 2026-01-02 04:57 | H87: 2026-01-02 04:57 | I87: Completed | J87: T-03 | K87: Tyrese Jackson | L87: 1.78 | M87: 409.64 | N87: 98.2 | O87: 91.24 | P87: 189.44 | Q87: 220.2 | R87: 5 | S87: Media | T87: 19096
A88: J-20087 | B88: C-10434 | C88: Gregory Peterson | D88: Leaking Pipe Repair | E88: Repair | F88: Standard | G88: 2025-12-24 15:08 | H88: 2025-12-25 15:08 | I88: Completed | J88: T-06 | K88: David Chen | L88: 1.56 | M88: 312.92 | N88: 88.83 | O88: 73.04 | P88: 161.87 | Q88: 151.05 | R88: 2 | S88: Drexel Hill | T88: 19072
A89: J-20088 | B89: C-10252 | C89: Joseph Hall | D89: AC Repair | E89: HVAC | F89: Standard | G89: 2024-10-28 23:28 | H89: 2024-10-28 23:28 | I89: Completed | J89: T-01 | K89: Mike Sullivan | L89: 2.9 | M89: 231.65 | N89: 73.37 | O89: 190.51 | P89: 263.88 | Q89: -32.23 | S89: Philadelphia | T89: 19197
A90: J-20089 | B90: C-10248 | C90: Miller Apartments | D90: Boiler Repair | E90: HVAC | F90: Standard | G90: 2025-12-15 01:45 | H90: 2025-12-15 01:45 | I90: Completed | J90: T-07 | K90: Kevin O'Brien | L90: 2.44 | M90: 1206.05 | N90: 272.99 | O90: 139.77 | P90: 412.76 | Q90: 793.29 | R90: 5 | S90: West Chester | T90: 19350
A91: J-20090 | B91: C-10502 | C91: Michelle Howard | D91: Slab Leak Repair | E91: Repair | F91: Standard | G91: 2024-10-16 09:19 | H91: 2024-10-18 09:19 | I91: Completed | J91: T-07 | K91: Kevin O'Brien | L91: 5.09 | M91: 3848.79 | N91: 949.01 | O91: 328.86 | P91: 1277.87 | Q91: 2570.92 | S91: Conshohocken | T91: 19470
A92: J-20091 | B92: C-10418 | C92: Torres Properties | D92: Leaking Pipe Repair | E92: Repair | F92: Standard | G92: 2025-03-26 14:53 | H92: 2025-03-26 14:53 | I92: Completed | J92: T-06 | K92: David Chen | L92: 1.06 | M92: 587.18 | N92: 98.4 | O92: 64.87 | P92: 163.27 | Q92: 423.91 | S92: Bryn Mawr | T92: 19051
A93: J-20092 | B93: C-10769 | C93: John Evans | D93: Drain Cleaning | E93: Drain | F93: Standard | G93: 2025-01-01 05:10 | H93: 2025-01-02 05:10 | I93: Completed | J93: T-07 | K93: Kevin O'Brien | L93: 0.99 | M93: 236.74 | N93: 70.61 | O93: 64.61 | P93: 135.22 | Q93: 101.52 | R93: 5 | S93: Bryn Mawr | T93: 19063
A94: J-20093 | B94: C-10450 | C94: Lopez Management | D94: Sewer Line Repair | E94: Repair | F94: Standard | G94: 2025-02-05 22:45 | H94: 2025-02-07 22:45 | I94: Completed | J94: T-05 | K94: Anthony Russo | L94: 4.32 | M94: 4013.2 | N94: 1296.06 | O94: 248.44 | P94: 1544.5 | Q94: 2468.7 | R94: 3 | S94: Conshohocken | T94: 19431
A95: J-20094 | B95: C-10670 | C95: Walker Management | D95: Boiler Repair | E95: HVAC | F95: Standard | G95: 2024-10-29 06:30 | I95: Completed | J95: T-02 | K95: Carlos Mendez | L95: 3.07 | M95: 812.56 | N95: 209.31 | O95: 167.56 | P95: 376.87 | Q95: 435.69 | R95: 2 | S95: King of Prussia | T95: 19470
A96: J-20095 | B96: C-10170 | C96: Nancy Ward | D96: Drain Cleaning | E96: Drain | F96: Standard | G96: 2025-08-26 03:27 | H96: 2025-08-26 03:27 | I96: Completed | J96: T-08 | K96: Marcus Thompson | L96: 1.14 | M96: 355.67 | N96: 64.74 | O96: 52.06 | P96: 116.8 | Q96: 238.87 | R96: 5 | S96: King of Prussia | T96: 19417
A97: J-20096 | B97: C-10821 | C97: Murphy Holdings | D97: Hydro Jetting | E97: Drain | F97: Urgent | G97: 2025-01-18 07:58 | H97: 2025-01-18 07:58 | I97: Completed | J97: T-02 | K97: Carlos Mendez | L97: 2.48 | M97: 717.81 | N97: 232.01 | O97: 162.39 | P97: 394.4 | Q97: 323.41 | R97: 3 | S97: King of Prussia | T97: 19443
A98: J-20097 | B98: C-10339 | C98: Stewart Building | D98: Slab Leak Repair | E98: Repair | F98: Standard | G98: 2025-09-17 21:21 | H98: 2025-09-17 21:21 | I98: Completed | J98: T-05 | K98: Anthony Russo | L98: 5.46 | M98: 3533.29 | N98: 540.98 | O98: 358.05 | P98: 899.03 | Q98: 2634.26 | R98: 5 | S98: Ardmore | T98: 19077
A99: J-20098 | B99: C-10199 | C99: Carolyn Rivera | D99: Frozen Pipe Thaw | E99: Emergency | F99: Emergency | G99: 2024-09-02 15:02 | I99: Completed | J99: T-01 | K99: Mike Sullivan | L99: 1.21 | M99: 604.79 | N99: 195.42 | O99: 68.4 | P99: 263.82 | Q99: 340.97 | R99: 5 | S99: Media | T99: 19082
A100: J-20099 | B100: C-10068 | C100: Rachel Cooper | D100: Sewer Line Inspection | E100: Diagnostic | F100: Standard | G100: 2024-12-22 13:21 | H100: 2024-12-22 13:21 | I100: Completed | J100: T-05 | K100: Anthony Russo | L100: 0.5 | M100: 409.96 | N100: 95.73 | O100: 23.58 | P100: 119.31 | Q100: 290.65 | S100: Bala Cynwyd | T100: 19093
...

Sheet Invoices
A1: Invoice ID | B1: Job ID | C1: Customer ID | D1: Customer Name | E1: Invoice Date | F1: Subtotal | G1: Tax | H1: Total | I1: Paid | J1: Paid Date | K1: Days to Pay | L1: Payment Method | M1: Status
A2: INV-50001 | B2: J-20001 | C2: C-10432 | D2: Karen Hill | E2: 2024-05-25 | F2: 665.95 | G2: 53.28 | H2: 719.23 | I2: Yes | J2: 2024-05-25 | K2: 0 | L2: Credit Card | M2: Paid
A3: INV-50002 | B3: J-20002 | C3: C-10747 | D3: Michelle Hernandez | E3: 2025-02-12 | F3: 3927.93 | G3: 314.23 | H3: 4242.16 | I3: Yes | J3: 2025-02-15 | K3: 3 | L3: ACH | M3: Paid
A4: INV-50003 | B4: J-20003 | C4: C-10794 | D4: Anthony Flores | E4: 2025-03-09 | F4: 569.33 | G4: 45.55 | H4: 614.88 | I4: Yes | J4: 2025-04-08 | K4: 30 | L4: ACH | M4: Paid
A5: INV-50004 | B5: J-20004 | C5: C-10697 | D5: Adams Management | E5: 2025-09-16 | F5: 257.31 | G5: 20.58 | H5: 277.89 | I5: Yes | J5: 2025-09-23 | K5: 7 | L5: Credit Card | M5: Paid
A6: INV-50005 | B6: J-20005 | C6: C-10628 | D6: Cruz Group | E6: 2026-03-30 | F6: 763.09 | G6: 61.05 | H6: 824.14 | I6: Yes | J6: 2026-05-29 | K6: 60 | L6: Financing | M6: Paid
A7: INV-50006 | B7: J-20006 | C7: C-10315 | D7: Scott Hill | E7: 2025-01-04 | F7: 275.18 | G7: 22.01 | H7: 297.19 | I7: Yes | J7: 2025-01-05 | K7: 1 | L7: Cash | M7: Paid
A8: INV-50007 | B8: J-20007 | C8: C-10546 | D8: Mary Davis | E8: 2025-07-27 | F8: 2004.42 | G8: 160.35 | H8: 2164.77 | I8: Yes | J8: 2025-07-30 | K8: 3 | L8: Credit Card | M8: Paid
A9: INV-50008 | B9: J-20011 | C9: C-10171 | D9: Sarah Evans | E9: 2025-07-01 | F9: 1818.36 | G9: 145.47 | H9: 1963.83 | I9: Yes | J9: 2025-07-02 | K9: 1 | L9: Credit Card | M9: Paid
A10: INV-50009 | B10: J-20012 | C10: C-10640 | D10: Jason White | E10: 2024-12-11 | F10: 361.31 | G10: 28.9 | H10: 390.21 | I10: Yes | J10: 2024-12-12 | K10: 1 | L10: Credit Card | M10: Paid
A11: INV-50010 | B11: J-20013 | C11: C-10803 | D11: Gonzalez LLC | E11: 2024-11-22 | F11: 662.16 | G11: 52.97 | H11: 715.13 | I11: Yes | J11: 2024-11-29 | K11: 7 | L11: Check | M11: Paid
A12: INV-50011 | B12: J-20014 | C12: C-10117 | D12: Garcia Building | E12: 2026-01-20 | F12: 379.58 | G12: 30.37 | H12: 409.95 | I12: Yes | J12: 2026-01-23 | K12: 3 | L12: Credit Card | M12: Paid
A13: INV-50012 | B13: J-20015 | C13: C-10827 | D13: Wright Center | E13: 2024-12-21 | F13: 216.25 | G13: 17.3 | H13: 233.55 | I13: Yes | J13: 2024-12-21 | K13: 0 | L13: Check | M13: Paid
... A30: INV-50029 | B30: J-20032 | C30: C-10458 | D30: White Building | E30: 2025-05-20 | F30: 499.61 | G30: 39.97 | H30: 539.58 | I30: Yes | J30: 2025-05-20 | K30: 0 | L30: Credit Card | M30: Paid
A31: INV-50030 | B31: J-20033 | C31: C-10331 | D31: Ronald Ward | E31: 2025-03-18 | F31: 317.62 | G31: 25.41 | H31: 343.03 | I31: No | M31: Open
A32: INV-50031 | B32: J-20034 | C32: C-10660 | D32: Brandon Thomas | E32: 2024-10-30 | F32: 362.76 | G32: 29.02 | H32: 391.78 | I32: Yes | J32: 2024-11-02 | K32: 3 | L32: Check | M32: Paid
A33: INV-50032 | B33: J-20035 | C33: C-10731 | D33: Martinez Holdings | E33: 2026-01-25 | F33: 296.42 | G33: 23.71 | H33: 320.13 | I33: Yes | J33: 2026-01-25 | K33: 0 | L33: Check | M33: Paid
A34: INV-50033 | B34: J-20036 | C34: C-10092 | D34: Jeffrey Ward | E34: 2025-07-13 | F34: 382.51 | G34: 30.6 | H34: 413.11 | I34: Yes | J34: 2025-07-16 | K34: 3 | L34: Credit Card | M34: Paid
A35: INV-50034 | B35: J-20037 | C35: C-10157 | D35: Clark Center | E35: 2024-10-31 | F35: 760.97 | G35: 60.88 | H35: 821.85 | I35: No | M35: Open
A36: INV-50035 | B36: J-20038 | C36: C-10214 | D36: Alexander Walker | E36: 2024-08-20 | F36: 341.55 | G36: 27.32 | H36: 368.87 | I36: Yes | J36: 2024-09-19 | K36: 30 | L36: Check | M36: Paid
A37: INV-50036 | B37: J-20039 | C37: C-10289 | D37: Ronald Gonzalez | E37: 2025-04-30 | F37: 2593.36 | G37: 207.47 | H37: 2800.83 | I37: Yes | J37: 2025-05-03 | K37: 3 | L37: Financing | M37: Paid
A38: INV-50037 | B38: J-20040 | C38: C-10668 | D38: Benjamin Flores | E38: 2026-02-23 | F38: 3206.28 | G38: 256.5 | H38: 3462.78 | I38: Yes | J38: 2026-02-24 | K38: 1 | L38: Credit Card | M38: Paid
A39: INV-50038 | B39: J-20041 | C39: C-10608 | D39: Thompson Building | E39: 2025-07-22 | F39: 717.35 | G39: 57.39 | H39: 774.74 | I39: No | M39: Open
A40: INV-50039 | B40: J-20044 | C40: C-10221 | D40: Linda Kim | E40: 2026-01-19 | F40: 442.24 | G40: 35.38 | H40: 477.62 | I40: Yes | J40: 2026-03-20 | K40: 60 | L40: Credit Card | M40: Paid
A41: INV-50040 | B41: J-20045 | C41: C-10820 | D41: Peterson Properties | E41: 2024-12-05 | F41: 1785.06 | G41: 142.8 | H41: 1927.86 | I41: Yes | J41: 2024-12-08 | K41: 3 | L41: Check | M41: Paid
A42: INV-50041 | B42: J-20046 | C42: C-10492 | D42: Thompson Apartments | E42: 2024-05-12 | F42: 404.43 | G42: 32.35 | H42: 436.78 | I42: Yes | J42: 2024-05-12 | K42: 0 | L42: Cash | M42: Paid
A43: INV-50042 | B43: J-20047 | C43: C-10046 | D43: Kim Management | E43: 2025-07-07 | F43: 2594.18 | G43: 207.53 | H43: 2801.71 | I43: Yes | J43: 2025-08-06 | K43: 30 | L43: Check | M43: Paid
A44: INV-50043 | B44: J-20048 | C44: C-10046 | D44: Kim Management | E44: 2024-04-17 | F44: 958.61 | G44: 76.69 | H44: 1035.3 | I44: Yes | J44: 2024-04-17 | K44: 0 | L44: Check | M44: Paid
A45: INV-50044 | B45: J-20049 | C45: C-10558 | D45: Ronald Gomez | E45: 2024-06-21 | F45: 551.79 | G45: 44.14 | H45: 595.93 | I45: Yes | J45: 2024-06-24 | K45: 3 | L45: Check | M45: Paid
A46: INV-50045 | B46: J-20050 | C46: C-10507 | D46: Robert Moore | E46: 2024-07-29 | F46: 3287.01 | G46: 262.96 | H46: 3549.97 | I46: Yes | J46: 2024-07-29 | K46: 0 | L46: ACH | M46: Paid
A47: INV-50046 | B47: J-20052 | C47: C-10406 | D47: Carter LLC | E47: 2024-09-26 | F47: 432.03 | G47: 34.56 | H47: 466.59 | I47: No | M47: Open
A48: INV-50047 | B48: J-20053 | C48: C-10807 | D48: Stephen Collins | E48: 2024-10-18 | F48: 352.29 | G48: 28.18 | H48: 380.47 | I48: Yes | J48: 2024-12-17 | K48: 60 | L48: Financing | M48: Paid
A49: INV-50048 | B49: J-20055 | C49: C-10311 | D49: Susan Perez | E49: 2025-06-08 | F49: 948.18 | G49: 75.85 | H49: 1024.03 | I49: Yes | J49: 2025-06-11 | K49: 3 | L49: Credit Card | M49: Paid
A50: INV-50049 | B50: J-20056 | C50: C-10678 | D50: Matthew Clark | E50: 2025-03-19 | F50: 227.75 | G50: 18.22 | H50: 245.97 | I50: Yes | J50: 2025-03-20 | K50: 1 | L50: Credit Card | M50: Paid
A51: INV-50050 | B51: J-20058 | C51: C-10390 | D51: Ashley Adams | E51: 2025-07-22 | F51: 2797.88 | G51: 223.83 | H51: 3021.71 | I51: Yes | J51: 2025-08-21 | K51: 30 | L51: ACH | M51: Paid
A52: INV-50051 | B52: J-20059 | C52: C-10248 | D52: Miller Apartments | E52: 2025-08-28 | F52: 1621.78 | G52: 129.74 | H52: 1751.52 | I52: Yes | J52: 2025-08-31 | K52: 3 | L52: Check | M52: Paid
A53: INV-50052 | B53: J-20060 | C53: C-10515 | D53: Robinson Realty | E53: 2024-10-05 | F53: 433.43 | G53: 34.67 | H53: 468.1 | I53: No | M53: Open
A54: INV-50053 | B54: J-20061 | C54: C-10167 | D54: Laura Cruz | E54: 2025-09-15 | F54: 1603.54 | G54: 128.28 | H54: 1731.82 | I54: Yes | J54: 2025-10-15 | K54: 30 | L54: Financing | M54: Paid
A55: INV-50054 | B55: J-20062 | C55: C-10349 | D55: Paul Jackson | E55: 2025-01-06 | F55: 1093.41 | G55: 87.47 | H55: 1180.88 | I55: Yes | J55: 2025-01-06 | K55: 0 | L55: ACH | M55: Paid
A56: INV-50055 | B56: J-20063 | C56: C-10022 | D56: Sharon Taylor | E56: 2025-06-25 | F56: 934.13 | G56: 74.73 | H56: 1008.86 | I56: Yes | J56: 2025-07-09 | K56: 14 | L56: ACH | M56: Paid
A57: INV-50056 | B57: J-20064 | C57: C-10250 | D57: Jennifer Martin | E57: 2024-05-26 | F57: 426.14 | G57: 34.09 | H57: 460.23 | I57: Yes | J57: 2024-07-25 | K57: 60 | L57: Check | M57: Paid
A58: INV-50057 | B58: J-20065 | C58: C-10190 | D58: William Howard | E58: 2024-04-18 | F58: 192.87 | G58: 15.43 | H58: 208.3 | I58: Yes | J58: 2024-05-18 | K58: 30 | L58: Credit Card | M58: Paid
A59: INV-50058 | B59: J-20066 | C59: C-10141 | D59: Ashley Cox | E59: 2025-09-25 | F59: 369.15 | G59: 29.53 | H59: 398.68 | I59: Yes | J59: 2025-10-02 | K59: 7 | L59: Credit Card | M59: Paid
A60: INV-50059 | B60: J-20067 | C60: C-10779 | D60: Margaret Gonzalez | E60: 2025-02-09 | F60: 206.78 | G60: 16.54 | H60: 223.32 | I60: Yes | J60: 2025-02-10 | K60: 1 | L60: Credit Card | M60: Paid
A61: INV-50060 | B61: J-20068 | C61: C-10198 | D61: Justin Robinson | E61: 2025-08-19 | F61: 3775.21 | G61: 302.02 | H61: 4077.23 | I61: Yes | J61: 2025-08-19 | K61: 0 | L61: Check | M61: Paid
A62: INV-50061 | B62: J-20069 | C62: C-10162 | D62: Brenda Diaz | E62: 2026-01-29 | F62: 379.62 | G62: 30.37 | H62: 409.99 | I62: Yes | J62: 2026-01-30 | K62: 1 | L62: Check | M62: Paid
A63: INV-50062 | B63: J-20070 | C63: C-10827 | D63: Wright Center | E63: 2025-05-26 | F63: 245.7 | G63: 19.66 | H63: 265.36 | I63: Yes | J63: 2025-05-26 | K63: 0 | L63: Credit Card | M63: Paid
A64: INV-50063 | B64: J-20071 | C64: C-10351 | D64: Richard Collins | E64: 2025-06-15 | F64: 220.22 | G64: 17.62 | H64: 237.84 | I64: Yes | J64: 2025-06-18 | K64: 3 | L64: ACH | M64: Paid
A65: INV-50064 | B65: J-20072 | C65: C-10846 | D65: Ronald Carter | E65: 2025-01-27 | F65: 288.53 | G65: 23.08 | H65: 311.61 | I65: Yes | J65: 2025-01-28 | K65: 1 | L65: ACH | M65: Paid
... A97: INV-50096 | B97: J-20104 | C97: C-10406 | D97: Carter LLC | E97: 2025-07-31 | F97: 190.68 | G97: 15.25 | H97: 205.93 | I97: Yes | J97: 2025-08-01 | K97: 1 | L97: ACH | M97: Paid
A98: INV-50097 | B98: J-20105 | C98: C-10756 | D98: Charles Murphy | E98: 2024-04-29 | F98: 400.18 | G98: 32.01 | H98: 432.19 | I98: No | M98: Open
A99: INV-50098 | B99: J-20106 | C99: C-10696 | D99: Susan Martinez | E99: 2026-01-08 | F99: 4282.92 | G99: 342.63 | H99: 4625.55 | I99: Yes | J99: 2026-01-08 | K99: 0 | L99: Check | M99: Paid
A100: INV-50099 | B100: J-20107 | C100: C-10842 | D100: Jennifer Edwards | E100: 2025-06-12 | F100: 1610.02 | G100: 128.8 | H100: 1738.82 | I100: Yes | J100: 2025-06-13 | K100: 1 | L100: Check | M100: Paid
A101: INV-50100 | B101: J-20108 | C101: C-10267 | D101: Jeffrey Perez | E101: 2024-07-24 | F101: 514.56 | G101: 41.16 | H101: 555.72 | I101: Yes | J101: 2024-08-23 | K101: 30 | L101: Check | M101: Paid
A102: INV-50101 | B102: J-20109 | C102: C-10368 | D102: Richard Morgan | E102: 2025-05-25 | F102: 832.32 | G102: 66.59 | H102: 898.91 | I102: Yes | J102: 2025-05-25 | K102: 0 | L102: Credit Card | M102: Paid
A103: INV-50102 | B103: J-20110 | C103: C-10121 | D103: Morris Holdings | E103: 2026-01-21 | F103: 421.61 | G103: 33.73 | H103: 455.34 | I103: Yes | J103: 2026-03-22 | K103: 60 | L103: Credit Card | M103: Paid
A104: INV-50103 | B104: J-20111 | C104: C-10688 | D104: Walker Apartments | E104: 2025-03-30 | F104: 284.28 | G104: 22.74 | H104: 307.02 | I104: No | M104: Open
A105: INV-50104 | B105: J-20112 | C105: C-10475 | D105: Rachel Kelly | E105: 2025-01-01 | F105: 4411.36 | G105: 352.91 | H105: 4764.27 | I105: Yes | J105: 2025-01-01 | K105: 0 | L105: ACH | M105: Paid
A106: INV-50105 | B106: J-20113 | C106: C-10717 | D106: Jonathan Sanchez | E106: 2025-04-30 | F106: 654.43 | G106: 52.35 | H106: 706.78 | I106: Yes | J106: 2025-04-30 | K106: 0 | L106: Credit Card | M106: Paid
A107: INV-50106 | B107: J-20114 | C107: C-10428 | D107: Gonzalez Holdings | E107: 2024-07-16 | F107: 2529.2 | G107: 202.34 | H107: 2731.54 | I107: Yes | J107: 2024-07-30 | K107: 14 | L107: Credit Card | M107: Paid
A108: INV-50107 | B108: J-20115 | C108: C-10755 | D108: Donna Rivera | E108: 2024-07-20 | F108: 6920.33 | G108: 553.63 | H108: 7473.96 | I108: Yes | J108: 2024-07-23 | K108: 3 | L108: Check | M108: Paid
A109: INV-50108 | B109: J-20116 | C109: C-10774 | D109: Amy Richardson | E109: 2024-07-04 | F109: 3101.5 | G109: 248.12 | H109: 3349.62 | I109: Yes | J109: 2024-07-04 | K109: 0 | L109: Credit Card | M109: Paid
A110: INV-50109 | B110: J-20117 | C110: C-10229 | D110: Edward Allen | E110: 2024-08-21 | F110: 7664.73 | G110: 613.18 | H110: 8277.91 | I110: Yes | J110: 2024-08-22 | K110: 1 | L110: Credit Card | M110: Paid
A111: INV-50110 | B111: J-20118 | C111: C-10078 | D111: James White | E111: 2025-02-05 | F111: 835.5 | G111: 66.84 | H111: 902.34 | I111: Yes | J111: 2025-02-08 | K111: 3 | L111: Credit Card | M111: Paid
A112: INV-50111 | B112: J-20119 | C112: C-10509 | D112: Miller Group | E112: 2025-03-04 | F112: 199.51 | G112: 15.96 | H112: 215.47 | I112: Yes | J112: 2025-03-07 | K112: 3 | L112: Financing | M112: Paid
A113: INV-50112 | B113: J-20120 | C113: C-10492 | D113: Thompson Apartments | E113: 2025-10-15 | F113: 208.87 | G113: 16.71 | H113: 225.58 | I113: Yes | J113: 2025-10-18 | K113: 3 | L113: Check | M113: Paid
A114: INV-50113 | B114: J-20121 | C114: C-10296 | D114: James Gutierrez | E114: 2025-12-03 | F114: 438.37 | G114: 35.07 | H114: 473.44 | I114: Yes | J114: 2025-12-04 | K114: 1 | L114: ACH | M114: Paid
A115: INV-50114 | B115: J-20122 | C115: C-10125 | D115: Stephen Lee | E115: 2025-12-02 | F115: 808 | G115: 64.64 | H115: 872.64 | I115: Yes | J115: 2025-12-05 | K115: 3 | L115: Check | M115: Paid
A116: INV-50115 | B116: J-20123 | C116: C-10257 | D116: Nguyen LLC | E116: 2026-02-01 | F116: 6472.97 | G116: 517.84 | H116: 6990.81 | I116: Yes | J116: 2026-02-04 | K116: 3 | L116: Check | M116: Paid
... A134: INV-50133 | B134: J-20142 | C134: C-10819 | D134: Donna Evans | E134: 2025-12-18 | F134: 464.14 | G134: 37.13 | H134: 501.27 | I134: Yes | J134: 2025-12-18 | K134: 0 | L134: Credit Card | M134: Paid
A135: INV-50134 | B135: J-20143 | C135: C-10004 | D135: Pamela Harris | E135: 2026-04-05 | F135: 619.48 | G135: 49.56 | H135: 669.04 | I135: No | M135: Open
A136: INV-50135 | B136: J-20144 | C136: C-10601 | D136: Frank Diaz | E136: 2024-09-05 | F136: 1343.38 | G136: 107.47 | H136: 1450.85 | I136: Yes | J136: 2024-09-12 | K136: 7 | L136: Credit Card | M136: Paid
A137: INV-50136 | B137: J-20145 | C137: C-10366 | D137: Shirley Evans | E137: 2024-04-30 | F137: 4345.89 | G137: 347.67 | H137: 4693.56 | I137: Yes | J137: 2024-05-14 | K137: 14 | L137: Credit Card | M137: Paid
A138: INV-50137 | B138: J-20146 | C138: C-10075 | D138: Rachel Allen | E138: 2025-11-19 | F138: 321.62 | G138: 25.73 | H138: 347.35 | I138: Yes | J138: 2025-11-19 | K138: 0 | L138: Check | M138: Paid
A139: INV-50138 | B139: J-20147 | C139: C-10659 | D139: Edward Wilson | E139: 2026-01-01 | F139: 176.22 | G139: 14.1 | H139: 190.32 | I139: Yes | J139: 2026-01-31 | K139: 30 | L139: Credit Card | M139: Paid
A140: INV-50139 | B140: J-20148 | C140: C-10555 | D140: Susan Gomez | E140: 2024-11-21 | F140: 520.78 | G140: 41.66 | H140: 562.44 | I140: Yes | J140: 2024-11-21 | K140: 0 | L140: Check | M140: Paid
A141: INV-50140 | B141: J-20149 | C141: C-10358 | D141: Edward Parker | E141: 2024-08-29 | F141: 760.54 | G141: 60.84 | H141: 821.38 | I141: Yes | J141: 2024-09-01 | K141: 3 | L141: ACH | M141: Paid
A142: INV-50141 | B142: J-20150 | C142: C-10136 | D142: Donald Clark | E142: 2025-11-20 | F142: 395.61 | G142: 31.65 | H142: 427.26 | I142: Yes | J142: 2025-11-23 | K142: 3 | L142: Check | M142: Paid
A143: INV-50142 | B143: J-20151 | C143: C-10705 | D143: Edward Adams | E143: 2025-10-10 | F143: 298.43 | G143: 23.87 | H143: 322.3 | I143: Yes | J143: 2025-10-24 | K143: 14 | L143: Check | M143: Paid
A144: INV-50143 | B144: J-20152 | C144: C-10717 | D144: Jonathan Sanchez | E144: 2024-05-15 | F144: 351.3 | G144: 28.1 | H144: 379.4 | I144: Yes | J144: 2024-05-29 | K144: 14 | L144: Credit Card | M144: Paid
A145: INV-50144 | B145: J-20153 | C145: C-10546 | D145: Mary Davis | E145: 2025-06-25 | F145: 2975.95 | G145: 238.08 | H145: 3214.03 | I145: Yes | J145: 2025-07-25 | K145: 30 | L145: Check | M145: Paid
A146: INV-50145 | B146: J-20154 | C146: C-10477 | D146: Jeffrey Morales | E146: 2026-02-10 | F146: 447.42 | G146: 35.79 | H146: 483.21 | I146: Yes | J146: 2026-02-11 | K146: 1 | L146: Financing | M146: Paid
A147: INV-50146 | B147: J-20155 | C147: C-10730 | D147: Kelly Group | E147: 2025-08-04 | F147: 3193.91 | G147: 255.51 | H147: 3449.42 | I147: Yes | J147: 2025-08-11 | K147: 7 | L147: Financing | M147: Paid
... A150: INV-50149 | B150: J-20159 | C150: C-10552 | D150: Rachel Moore | E150: 2025-04-10 | F150: 609.54 | G150: 48.76 | H150: 658.3 | I150: Yes | J150: 2025-04-10 | K150: 0 | L150: Check | M150: Paid
A151: INV-50150 | B151: J-20160 | C151: C-10833 | D151: David Thompson | E151: 2024-11-21 | F151: 589.12 | G151: 47.13 | H151: 636.25 | I151: No | M151: Open
A152: INV-50151 | B152: J-20161 | C152: C-10322 | D152: Steven Perez | E152: 2024-05-29 | F152: 346.5 | G152: 27.72 | H152: 374.22 | I152: Yes | J152: 2024-06-05 | K152: 7 | L152: Financing | M152: Paid
A153: INV-50152 | B153: J-20162 | C153: C-10387 | D153: Evans Apartments | E153: 2024-10-30 | F153: 179.75 | G153: 14.38 | H153: 194.13 | I153: Yes | J153: 2024-11-02 | K153: 3 | L153: Check | M153: Paid
A154: INV-50153 | B154: J-20163 | C154: C-10732 | D154: Michelle Gutierrez | E154: 2024-09-12 | F154: 1741.08 | G154: 139.29 | H154: 1880.37 | I154: Yes | J154: 2024-09-15 | K154: 3 | L154: ACH | M154: Paid
A155: INV-50154 | B155: J-20164 | C155: C-10126 | D155: Daniel Turner | E155: 2024-09-14 | F155: 765.64 | G155: 61.25 | H155: 826.89 | I155: Yes | J155: 2024-09-28 | K155: 14 | L155: Credit Card | M155: Paid
A156: INV-50155 | B156: J-20165 | C156: C-10255 | D156: Robinson Plaza | E156: 2025-08-01 | F156: 518.84 | G156: 41.51 | H156: 560.35 | I156: Yes | J156: 2025-08-02 | K156: 1 | L156: Check | M156: Paid
A157: INV-50156 | B157: J-20166 | C157: C-10661 | D157: Joshua Morales | E157: 2026-03-16 | F157: 3617.49 | G157: 289.4 | H157: 3906.89 | I157: Yes | J157: 2026-03-16 | K157: 0 | L157: Cash | M157: Paid
A158: INV-50157 | B158: J-20167 | C158: C-10085 | D158: Kathleen Reed | E158: 2025-04-08 | F158: 4497.68 | G158: 359.81 | H158: 4857.49 | I158: Yes | J158: 2025-04-08 | K158: 0 | L158: Credit Card | M158: Paid
A159: INV-50158 | B159: J-20168 | C159: C-10192 | D159: Cynthia Flores | E159: 2024-05-22 | F159: 331 | G159: 26.48 | H159: 357.48 | I159: Yes | J159: 2024-06-05 | K159: 14 | L159: Credit Card | M159: Paid
A160: INV-50159 | B160: J-20169 | C160: C-10544 | D160: Nancy Thompson | E160: 2024-04-22 | F160: 537.93 | G160: 43.03 | H160: 580.96 | I160: Yes | J160: 2024-04-22 | K160: 0 | L160: Cash | M160: Paid
A161: INV-50160 | B161: J-20171 | C161: C-10539 | D161: Gary Phillips | E161: 2025-12-23 | F161: 2418.14 | G161: 193.45 | H161: 2611.59 | I161: Yes | J161: 2025-12-30 | K161: 7 | L161: Credit Card | M161: Paid
A162: INV-50161 | B162: J-20172 | C162: C-10204 | D162: Allen Plaza | E162: 2025-08-28 | F162: 343.66 | G162: 27.49 | H162: 371.15 | I162: Yes | J162: 2025-08-28 | K162: 0 | L162: Credit Card | M162: Paid
A163: INV-50162 | B163: J-20173 | C163: C-10086 | D163: John Davis | E163: 2024-12-20 | F163: 224.84 | G163: 17.99 | H163: 242.83 | I163: Yes | J163: 2024-12-20 | K163: 0 | L163: Cash | M163: Paid
... A201: INV-50200 | B201: J-20212 | C201: C-10447 | D201: Reyes LLC | E201: 2025-11-25 | F201: 673.61 | G201: 53.89 | H201: 727.5 | I201: Yes | J201: 2025-12-25 | K201: 30 | L201: ACH | M201: Paid
A202: INV-50201 | B202: J-20213 | C202: C-10699 | D202: Helen Miller | E202: 2025-04-02 | F202: 593.65 | G202: 47.49 | H202: 641.14 | I202: No | M202: Open
A203: INV-50202 | B203: J-20214 | C203: C-10555 | D203: Susan Gomez | E203: 2025-07-23 | F203: 575.27 | G203: 46.02 | H203: 621.29 | I203: Yes | J203: 2025-07-23 | K203: 0 | L203: Check | M203: Paid
...

Sheet Calls
A1: Call ID | B1: Timestamp | C1: Phone | D1: Duration (min) | E1: Answered | F1: After Hours | G1: Lead Source | H1: Intent | I1: Booked | J1: Converted | K1: Revenue Attributed
A2: CL-30001 | B2: 2025-12-21 23:05 | C2: (380) 569-8067 | D2: 3.9 | E2: Yes | F2: Yes | G2: HomeAdvisor | H2: Leak | I2: Yes | J2: No | K2: 0
A3: CL-30002 | B3: 2026-01-16 15:43 | C3: (247) 259-4125 | D3: 2.5 | E3: Yes | F3: No | G3: Direct Mail | H3: Drain Clog | I3: Yes | J3: No | K3: 0
A4: CL-30003 | B4: 2025-11-25 20:39 | C4: (295) 456-1619 | D4: 5.2 | E4: Yes | F4: Yes | G4: Repeat Customer | H4: Burst Pipe | I4: Yes | J4: Yes | K4: 3107.96
A5: CL-30004 | B5: 2025-02-15 00:39 | C5: (425) 278-3158 | D5: 5.5 | E5: No | F5: Yes | G5: Yelp | H5: Other | I5: No | J5: No | K5: 0
A6: CL-30005 | B6: 2025-12-01 11:08 | C6: (254) 265-3698 | D6: 5.9 | E6: Yes | F6: No | G6: Google Ads | H6: Drain Clog | I6: No | J6: No | K6: 0
A7: CL-30006 | B7: 2025-09-06 16:16 | C7: (535) 599-8613 | D7: 0.3 | E7: Yes | F7: Yes | G7: HomeAdvisor | H7: HVAC | I7: Yes | J7: Yes | K7: 3144.86
A8: CL-30007 | B8: 2025-07-29 18:46 | C8: (473) 514-2629 | D8: 1.3 | E8: No | F8: Yes | G8: Referral | H8: Sewer | I8: No | J8: No | K8: 0
A9: CL-30008 | B9: 2025-06-10 16:41 | C9: (226) 967-8973 | D9: 3.3 | E9: Yes | F9: No | G9: Facebook | H9: Burst Pipe | I9: No | J9: No | K9: 0
A10: CL-30009 | B10: 2025-07-10 02:22 | C10: (588) 828-7016 | D10: 3.1 | E10: Yes | F10: Yes | G10: Google Search | H10: HVAC | I10: No | J10: No | K10: 0
A11: CL-30010 | B11: 2026-03-30 04:12 | C11: (483) 856-2125 | D11: 2.8 | E11: No | F11: Yes | G11: Repeat Customer | H11: Leak | I11: No | J11: No | K11: 0
A12: CL-30011 | B12: 2025-01-15 06:46 | C12: (277) 251-7106 | D12: 2.7 | E12: Yes | F12: Yes | G12: Truck Signage | H12: Leak | I12: Yes | J12: Yes | K12: 1589.93
A13: CL-30012 | B13: 2026-01-15 12:13 | C13: (388) 544-2492 | D13: 5.3 | E13: Yes | F13: No | G13: Google Search | H13: HVAC | I13: No | J13: No | K13: 0
... A3201: CL-33200 | B3201: 2025-12-15 06:05 | C3201: (557) 478-6731 | D3201: 2.8 | E3201: Yes | F3201: Yes | G3201: Google Search | H3201: Drain Clog | I3201: Yes | J3201: Yes | K3201: 329.93

Sheet Reviews
A1: Review ID | B1: Date | C1: Platform | D1: Stars | E1: Review Text | F1: Responded | G1: Tech Mentioned
A2: R-40001 | B2: 2025-11-07 | C2: Yelp | D2: 5 | E2: Showed up on time and fixed the problem fast. | F2: Yes
A3: R-40002 | B3: 2025-12-13 | C3: Google | D3: 5 | E3: Fixed our water heater in under 2 hours. Great service. | F3: Yes
A4: R-40003 | B4: 2025-06-20 | C4: Angi | D4: 5 | E4: Fixed our water heater in under 2 hours. Great service. | F4: Yes
A5: R-40004 | B5: 2024-05-23 | C5: Google | D5: 5 | E5: Tech was professional and explained everything. | F5: Yes
A6: R-40005 | B6: 2025-02-10 | C6: Google | D6: 5 | E6: They came the same day for an emergency. Lifesavers. | F6: Yes | G6: Kevin O'Brien
A7: R-40006 | B7: 2025-08-21 | C7: Google | D7: 4 | E7: Mike was awesome — knowledgeable and friendly. | F7: Yes
A8: R-40007 | B8: 2024-06-19 | C8: Google | D8: 5 | E8: Fair price and great work. Will use again. | F8: Yes | G8: David Chen
A9: R-40008 | B9: 2026-01-08 | C9: Google | D9: 3 | E9: Work was solid but the wait window was too long. | F9: Yes | G9: Anthony Russo
A10: R-40009 | B10: 2025-05-04 | C10: BBB | D10: 5 | E10: Best plumbing experience I've had in Philly. A+. | F10: Yes
A11: R-40010 | B11: 2024-10-05 | C11: Google | D11: 5 | E11: Quick response, clean work, no upselling. | F11: Yes
A12: R-40011 | B12: 2024-12-14 | C12: Google | D12: 5 | E12: Mike was awesome — knowledgeable and friendly. | F12: Yes
A13: R-40012 | B13: 2025-05-08 | C13: Google | D13: 5 | E13: Fair price and great work. Will use again. | F13: Yes
A14: R-40013 | B14: 2025-10-11 | C14: Angi | D14: 5 | E14: Showed up on time and fixed the problem fast. | F14: Yes
A15: R-40014 | B15: 2024-06-29 | C15: Yelp | D15: 4 | E15: Quote was exactly what they charged. No surprises. | F15: Yes | G15: Tyrese Jackson
A16: R-40015 | B16: 2025-03-08 | C16: Google | D16: 5 | E16: Highly recommend Keystone — saved us from a flood at 2am. | F16: Yes
A17: R-40016 | B17: 2025-05-27 | C17: Angi | D17: 5 | E17: Fair price and great work. Will use again. | F17: Yes
A18: R-40017 | B18: 2024-07-22 | C18: Yelp | D18: 5 | E18: Highly recommend Keystone — saved us from a flood at 2am. | F18: Yes | G18: Carlos Mendez
A19: R-40018 | B19: 2025-08-17 | C19: Yelp | D19: 5 | E19: Quote was exactly what they charged. No surprises. | F19: Yes | G19: Kevin O'Brien
A20: R-40019 | B20: 2025-05-12 | C20: Google | D20: 5 | E20: Tech was professional and explained everything. | F20: Yes
A21: R-40020 | B21: 2026-03-20 | C21: Google | D21: 5 | E21: Showed up on time and fixed the problem fast. | F21: Yes
A22: R-40021 | B22: 2024-07-26 | C22: Google | D22: 5 | E22: They came the same day for an emergency. Lifesavers. | F22: Yes
A23: R-40022 | B23: 2024-05-24 | C23: Google | D23: 4 | E23: Quick response, clean work, no upselling. | F23: Yes
A24: R-40023 | B24: 2024-07-10 | C24: Google | D24: 5 | E24: Highly recommend Keystone — saved us from a flood at 2am. | F24: Yes
A25: R-40024 | B25: 2024-05-21 | C25: Google | D25: 5 | E25: Fair price and great work. Will use again. | F25: Yes
A26: R-40025 | B26: 2025-04-25 | C26: Yelp | D26: 5 | E26: They came the same day for an emergency. Lifesavers. | F26: No | G26: Tyrese Jackson
A27: R-40026 | B27: 2024-07-10 | C27: Facebook | D27: 5 | E27: Highly recommend Keystone — saved us from a flood at 2am. | F27: Yes | G27: Carlos Mendez
A28: R-40027 | B28: 2024-05-06 | C28: Google | D28: 5 | E28: Quote was exactly what they charged. No surprises. | F28: Yes
A29: R-40028 | B29: 2024-07-25 | C29: Google | D29: 4 | E29: Quote was exactly what they charged. No surprises. | F29: Yes | G29: Brandon Pierce
A30: R-40029 | B30: 2025-12-09 | C30: Yelp | D30: 5 | E30: They came the same day for an emergency. Lifesavers. | F30: Yes
A31: R-40030 | B31: 2025-05-30 | C31: Google | D31: 5 | E31: Quote was exactly what they charged. No surprises. | F31: No
A32: R-40031 | B32: 2025-04-21 | C32: Yelp | D32: 5 | E32: Tech was professional and explained everything. | F32: Yes
A33: R-40032 | B33: 2025-12-14 | C33: Yelp | D33: 5 | E33: Fair price and great work. Will use again. | F33: Yes
A34: R-40033 | B34: 2026-02-10 | C34: BBB | D34: 5 | E34: Quote was exactly what they charged. No surprises. | F34: Yes
A35: R-40034 | B35: 2024-07-16 | C35: Google | D35: 5 | E35: Highly recommend Keystone — saved us from a flood at 2am. | F35: No
A36: R-40035 | B36: 2025-04-28 | C36: Angi | D36: 5 | E36: Highly recommend Keystone — saved us from a flood at 2am. | F36: Yes | G36: Tyrese Jackson
A37: R-40036 | B37: 2024-11-17 | C37: Google | D37: 5 | E37: Fair price and great work. Will use again. | F37: Yes
A38: R-40037 | B38: 2024-05-08 | C38: Yelp | D38: 5 | E38: Quote was exactly what they charged. No surprises. | F38: Yes
A39: R-40038 | B39: 2025-10-30 | C39: Google | D39: 5 | E39: Highly recommend Keystone — saved us from a flood at 2am. | F39: Yes | G39: Anthony Russo
A40: R-40039 | B40: 2024-10-28 | C40: Google | D40: 5 | E40: Fair price and great work. Will use again. | F40: Yes
A41: R-40040 | B41: 2024-09-20 | C41: Google | D41: 4 | E41: Fixed our water heater in under 2 hours. Great service. | F41: Yes | G41: David Chen
A42: R-40041 | B42: 2024-08-31 | C42: Facebook | D42: 5 | E42: Fixed our water heater in under 2 hours. Great service. | F42: Yes
A43: R-40042 | B43: 2025-04-25 | C43: BBB | D43: 2 | E43: Waited 3 hours past my appointment window. Frustrating. | F43: Yes | G43: David Chen
A44: R-40043 | B44: 2026-02-22 | C44: Google | D44: 2 | E44: Job took longer than promised and price kept climbing. | F44: Yes
A45: R-40044 | B45: 2025-12-24 | C45: Google | D45: 5 | E45: Tech was professional and explained everything. | F45: Yes | G45: David Chen
A46: R-40045 | B46: 2026-02-16 | C46: Google | D46: 5 | E46: Mike was awesome — knowledgeable and friendly. | F46: Yes | G46: Brandon Pierce
A47: R-40046 | B47: 2025-11-26 | C47: Google | D47: 5 | E47: Fixed our water heater in under 2 hours. Great service. | F47: Yes
A48: R-40047 | B48: 2024-09-07 | C48: Google | D48: 5 | E48: Fair price and great work. Will use again. | F48: Yes
A49: R-40048 | B49: 2024-11-08 | C49: Yelp | D49: 5 | E49: Highly recommend Keystone — saved us from a flood at 2am. | F49: Yes
A50: R-40049 | B50: 2025-01-22 | C50: Google | D50: 5 | E50: Fixed our water heater in under 2 hours. Great service. | F50: Yes | G50: Brandon Pierce
A51: R-40050 | B51: 2025-01-08 | C51: Angi | D51: 4 | E51: Mike was awesome — knowledgeable and friendly. | F51: Yes | G51: Kevin O'Brien
A52: R-40051 | B52: 2026-04-04 | C52: Angi | D52: 1 | E52: Waited 3 hours past my appointment window. Frustrating. | F52: No
A53: R-40052 | B53: 2025-08-29 | C53: Google | D53: 4 | E53: Fair price and great work. Will use again. | F53: Yes | G53: Mike Sullivan
A54: R-40053 | B54: 2025-05-25 | C54: Facebook | D54: 5 | E54: Mike was awesome — knowledgeable and friendly. | F54: Yes
A55: R-40054 | B55: 2025-12-18 | C55: Google | D55: 3 | E55: Got the job done but had to reschedule once. | F55: Yes | G55: Kevin O'Brien
A56: R-40055 | B56: 2024-11-24 | C56: Google | D56: 5 | E56: Tech was professional and explained everything. | F56: Yes
A57: R-40056 | B57: 2025-07-29 | C57: Yelp | D57: 5 | E57: Quick response, clean work, no upselling. | F57: Yes | G57: David Chen
A58: R-40057 | B58: 2024-05-21 | C58: Google | D58: 4 | E58: Best plumbing experience I've had in Philly. A+. | F58: Yes | G58: Tyrese Jackson
A59: R-40058 | B59: 2025-03-09 | C59: Google | D59: 5 | E59: Tech was professional and explained everything. | F59: Yes
A60: R-40059 | B60: 2025-02-22 | C60: Google | D60: 5 | E60: They came the same day for an emergency. Lifesavers. | F60: Yes | G60: Marcus Thompson
A61: R-40060 | B61: 2025-08-21 | C61: Yelp | D61: 2 | E61: Quoted one price, charged another. Not happy. | F61: Yes
A62: R-40061 | B62: 2025-10-06 | C62: Google | D62: 5 | E62: Quick response, clean work, no upselling. | F62: Yes
A63: R-40062 | B63: 2026-01-15 | C63: Google | D63: 5 | E63: Showed up on time and fixed the problem fast. | F63: Yes
A64: R-40063 | B64: 2025-11-28 | C64: Angi | D64: 4 | E64: Tech was professional and explained everything. | F64: Yes | G64: Marcus Thompson
A65: R-40064 | B65: 2025-05-17 | C65: Yelp | D65: 5 | E65: Best plumbing experience I've had in Philly. A+. | F65: Yes
A66: R-40065 | B66: 2026-02-28 | C66: Google | D66: 5 | E66: Showed up on time and fixed the problem fast. | F66: Yes
A67: R-40066 | B67: 2024-12-29 | C67: Google | D67: 5 | E67: Fixed our water heater in under 2 hours. Great service. | F67: Yes | G67: Anthony Russo
A68: R-40067 | B68: 2026-03-29 | C68: Google | D68: 5 | E68: Mike was awesome — knowledgeable and friendly. | F68: Yes
A69: R-40068 | B69: 2026-02-23 | C69: Angi | D69: 5 | E69: Showed up on time and fixed the problem fast. | F69: Yes | G69: Marcus Thompson
A70: R-40069 | B70: 2024-07-25 | C70: Google | D70: 5 | E70: Quick response, clean work, no upselling. | F70: Yes | G70: Brandon Pierce
A71: R-40070 | B71: 2025-12-02 | C71: Google | D71: 5 | E71: Fair price and great work. Will use again. | F71: Yes
A72: R-40071 | B72: 2026-01-12 | C72: Google | D72: 5 | E72: Best plumbing experience I've had in Philly. A+. | F72: Yes
A73: R-40072 | B73: 2025-11-26 | C73: Yelp | D73: 5 | E73: Fair price and great work. Will use again. | F73: Yes
A74: R-40073 | B74: 2025-01-31 | C74: Google | D74: 3 | E74: Tech was good, office communication could improve. | F74: Yes
A75: R-40074 | B75: 2025-05-25 | C75: Google | D75: 5 | E75: Mike was awesome — knowledgeable and friendly. | F75: Yes
A76: R-40075 | B76: 2025-05-03 | C76: Google | D76: 4 | E76: Showed up on time and fixed the problem fast. | F76: Yes | G76: Kevin O'Brien
A77: R-40076 | B77: 2025-06-29 | C77: Google | D77: 5 | E77: Quote was exactly what they charged. No surprises. | F77: Yes
A78: R-40077 | B78: 2025-09-21 | C78: Google | D78: 5 | E78: Tech was professional and explained everything. | F78: No
A79: R-40078 | B79: 2025-12-20 | C79: Google | D79: 5 | E79: Highly recommend Keystone — saved us from a flood at 2am. | F79: No | G79: Tyrese Jackson
A80: R-40079 | B80: 2024-12-22 | C80: Google | D80: 5 | E80: They came the same day for an emergency. Lifesavers. | F80: No
A81: R-40080 | B81: 2025-05-17 | C81: Google | D81: 5 | E81: Mike was awesome — knowledgeable and friendly. | F81: Yes | G81: Kevin O'Brien
A82: R-40081 | B82: 2024-06-07 | C82: Yelp | D82: 3 | E82: Tech was good, office communication could improve. | F82: Yes
A83: R-40082 | B83: 2025-12-17 | C83: Google | D83: 4 | E83: Best plumbing experience I've had in Philly. A+. | F83: Yes
A84: R-40083 | B84: 2025-01-22 | C84: Google | D84: 5 | E84: Fair price and great work. Will use again. | F84: Yes | G84: Tyrese Jackson
A85: R-40084 | B85: 2026-02-04 | C85: BBB | D85: 5 | E85: They came the same day for an emergency. Lifesavers. | F85: No | G85: David Chen
A86: R-40085 | B86: 2025-08-14 | C86: Google | D86: 5 | E86: Tech was professional and explained everything. | F86: Yes
A87: R-40086 | B87: 2025-02-01 | C87: Google | D87: 4 | E87: Quote was exactly what they charged. No surprises. | F87: Yes
A88: R-40087 | B88: 2024-06-25 | C88: Facebook | D88: 5 | E88: Fixed our water heater in under 2 hours. Great service. | F88: No
A89: R-40088 | B89: 2024-08-02 | C89: Yelp | D89: 5 | E89: Best plumbing experience I've had in Philly. A+. | F89: No | G89: Anthony Russo
A90: R-40089 | B90: 2025-08-05 | C90: Yelp | D90: 5 | E90: Tech was professional and explained everything. | F90: Yes
A91: R-40090 | B91: 2025-03-28 | C91: Yelp | D91: 5 | E91: Showed up on time and fixed the problem fast. | F91: Yes | G91: Anthony Russo
A92: R-40091 | B92: 2024-11-08 | C92: Google | D92: 5 | E92: Best plumbing experience I've had in Philly. A+. | F92: Yes
A93: R-40092 | B93: 2025-03-08 | C93: Google | D93: 5 | E93: Showed up on time and fixed the problem fast. | F93: Yes | G93: Kevin O'Brien
A94: R-40093 | B94: 2025-08-16 | C94: Google | D94: 2 | E94: Waited 3 hours past my appointment window. Frustrating. | F94: No
A95: R-40094 | B95: 2024-08-31 | C95: Facebook | D95: 5 | E95: Fair price and great work. Will use again. | F95: Yes
A96: R-40095 | B96: 2025-11-08 | C96: Yelp | D96: 5 | E96: They came the same day for an emergency. Lifesavers. | F96: Yes | G96: Anthony Russo
A97: R-40096 | B97: 2025-08-30 | C97: Yelp | D97: 5 | E97: Fixed our water heater in under 2 hours. Great service. | F97: Yes | G97: Marcus Thompson
A98: R-40097 | B98: 2026-04-02 | C98: Google | D98: 5 | E98: They came the same day for an emergency. Lifesavers. | F98: No
A99: R-40098 | B99: 2025-04-01 | C99: Yelp | D99: 5 | E99: They came the same day for an emergency. Lifesavers. | F99: Yes
A100: R-40099 | B100: 2025-06-03 | C100: Google | D100: 5 | E100: Showed up on time and fixed the problem fast. | F100: Yes | G100: Mike Sullivan
...

Sheet Technicians
A1: Tech ID | B1: Name | C1: License | D1: Level | E1: Years Experience | F1: Avg Rating
A2: T-01 | B2: Mike Sullivan | C2: Master Plumber | D2: Senior | E2: 18 | F2: 4.9
A3: T-02 | B3: Carlos Mendez | C3: Journeyman | D3: Senior | E3: 11 | F3: 4.8
A4: T-03 | B4: Tyrese Jackson | C4: Journeyman | D4: Mid | E4: 6 | F4: 4.7
A5: T-04 | B5: Brandon Pierce | C5: Journeyman | D5: Mid | E5: 7 | F5: 4.6
A6: T-05 | B6: Anthony Russo | C6: Apprentice | D6: Junior | E6: 2 | F6: 4.5
A7: T-06 | B7: David Chen | C7: Master Plumber | D7: Senior | E7: 15 | F7: 4.9
A8: T-07 | B8: Kevin O'Brien | C8: Journeyman | D8: Mid | E8: 9 | F8: 4.4
A9: T-08 | B9: Marcus Thompson | C9: Apprentice | D9: Junior | E9: 3 | F9: 4.6

Sheet Parts Inventory
A1: Part ID | B1: Description | C1: Category | D1: Unit Cost | E1: On Hand
A2: P-1001 | B2: 1/2" Copper Pipe (10ft) | C2: Pipe | D2: 18.5 | E2: 42
A3: P-1002 | B3: 3/4" Copper Pipe (10ft) | C3: Pipe | D3: 26.75 | E3: 38
A4: P-1003 | B4: 1" PVC Pipe (10ft) | C4: Pipe | D4: 8.25 | E4: 75
A5: P-1004 | B5: Wax Toilet Ring | C5: Toilet | D5: 4.5 | E5: 120
A6: P-1005 | B6: Toilet Flapper | C6: Toilet | D6: 6.25 | E6: 85
A7: P-1006 | B7: Toilet Fill Valve | C7: Toilet | D7: 14.5 | E7: 60
A8: P-1007 | B8: 40-Gal Gas Water Heater | C8: Water Heater | D8: 685 | E8: 8
A9: P-1008 | B9: 50-Gal Gas Water Heater | C9: Water Heater | D9: 825 | E9: 6
A10: P-1009 | B10: Tankless Water Heater | C10: Water Heater | D10: 1685 | E10: 4
A11: P-1010 | B11: Garbage Disposal 3/4 HP | C11: Disposal | D11: 185 | E11: 12
A12: P-1011 | B12: Kitchen Faucet (Standard) | C12: Faucet | D12: 125 | E12: 18
A13: P-1012 | B13: Bathroom Faucet (Standard) | C13: Faucet | D13: 85 | E13: 22
... A26: P-1025 | B26: Pipe Insulation (10ft) | C26: Insulation | D26: 12.25 | E26: 40

Sheet Summary KPIs
A1: KEYSTONE PLUMBING — KPI SUMMARY
A3: REVENUE
A4: Total Revenue (all time) | B4: =SUM(Jobs!M2:M2401) -> 3288961.8
A5: Total Margin | B5: =SUM(Jobs!Q2:Q2401) -> 2028348.8
A6: Margin % | B6: =SUM(Jobs!Q2:Q2401)/SUM(Jobs!M2:M2401) -> 0.61671401
A7: Average Job Ticket | B7: =AVERAGE(Jobs!M2:M2401) -> 1370.4008
A9: JOBS
A10: Total Jobs | B10: =COUNTA(Jobs!A2:A2401) -> 2400
A11: Completed Jobs | B11: =COUNTIF(Jobs!I2:I2401,"Completed") -> 2266
A12: Cancelled Jobs | B12: =COUNTIF(Jobs!I2:I2401,"Cancelled") -> 72
A13: No-Shows | B13: =COUNTIF(Jobs!I2:I2401,"No-Show") -> 20
A15: CUSTOMERS
A16: Total Customers | B16: =COUNTA(Customers!A2:A851) -> 850
A17: Residential | B17: =COUNTIF(Customers!C2:C851,"Residential") -> 570
A18: Commercial | B18: =COUNTIF(Customers!C2:C851,"Commercial") -> 179
A19: Property Mgmt | B19: =COUNTIF(Customers!C2:C851,"Property Mgmt") -> 101
A21: CALLS / LEADS
A22: Total Inbound Calls | B22: =COUNTA(Calls!A2:A3201) -> 3200
A23: Calls Answered | B23: =COUNTIF(Calls!E2:E3201,"Yes") -> 2292
A24: Answer Rate | B24: =COUNTIF(Calls!E2:E3201,"Yes")/COUNTA(Calls!A2:A3201) -> 0.71625
A25: After-Hours Calls | B25: =COUNTIF(Calls!F2:F3201,"Yes") -> 2147
A26: Calls Booked | B26: =COUNTIF(Calls!I2:I3201,"Yes") -> 1093
A27: Booking Rate (of answered) | B27: =COUNTIF(Calls!I2:I3201,"Yes")/COUNTIF(Calls!E2:E3201,"Yes") -> 0.47687609
A28: Missed-Call Revenue Risk (est) | B28: =(COUNTA(Calls!A2:A3201)-COUNTIF(Calls!E2:E3201,"Yes"))*AVERAGEIF(Calls!J2:J3201,"Yes",Calls!K2:K3201)*0.4 -> 621163.53
A30: REVIEWS
A31: Total Reviews | B31: =COUNTA(Reviews!A2:A421) -> 420
A32: Average Stars | B32: =AVERAGE(Reviews!D2:D421) -> 4.5
A33: 5-Star Reviews | B33: =COUNTIF(Reviews!D2:D421,5) -> 295
A34: 1-2 Star Reviews | B34: =COUNTIF(Reviews!D2:D421,"<=2") -> 27
A35: Response Rate | B35: =COUNTIF(Reviews!F2:F421,"Yes")/COUNTA(Reviews!A2:A421) -> 0.81428571
A37: INVOICES
A38: Total Invoiced | B38: =SUM(Invoices!H2:H2267) -> 3365773.7
A39: Outstanding (Open + Overdue) | B39: =SUMIFS(Invoices!H2:H2267,Invoices!I2:I2267,"No") -> 176286.59
A40: Avg Days to Pay | B40: =AVERAGEIF(Invoices!I2:I2267,"Yes",Invoices!K2:K2267) -> 9.4073901
